[
  {
    "type": "Video",
    "caption": "",
    "hashtags": [],
    "mentions": [],
    "commentsCount": 4686,
    "likesCount": 38423,
    "videoViewCount": 103106,
    "videoPlayCount": 292386,
    "timestamp": "2024-10-04T05:13:48.000Z",
    "ownerFullName": "Eduardo Braide",
    "ownerUsername": "eduardobraide",
    "videoDuration": 88.133
  },
  {
    "type": "Video",
    "caption": "✨ O trabalho por aqui não para! 🚧\n\nHoje foi dia de fiscalizar o asfalto novo na Vila Maranhão e Vila Tiradentes! 🎉\n\nEstou acompanhando tudo de perto, e o asfalto é de 5cm com brita, vai garantir qualidade para todas as ruas que precisam! 🛣️\n\nAlém disso, a iluminação de LED tá chegando pra mudar as noites da Vila Maranhão e Vila Tiradentes, fazendo a noite virar dia! 😎☀️\n\n#BraideTrabalha\n#PrefeitoPresente",
    "hashtags": [
      "BraideTrabalha",
      "PrefeitoPresente"
    ],
    "mentions": [],
    "commentsCount": 1072,
    "likesCount": 15249,
    "videoViewCount": 63757,
    "videoPlayCount": 220023,
    "timestamp": "2024-10-04T16:15:34.000Z",
    "ownerFullName": "Eduardo Braide",
    "ownerUsername": "eduardobraide",
    "videoDuration": 37.733
  },
  {
    "type": "Video",
    "caption": "Pelo visto, esse debate virou uns votinhos...",
    "hashtags": [],
    "mentions": [],
    "commentsCount": 7044,
    "likesCount": 39815,
    "videoViewCount": 246372,
    "videoPlayCount": 937270,
    "timestamp": "2024-10-04T05:31:19.000Z",
    "ownerFullName": "Eduardo Braide",
    "ownerUsername": "eduardobraide",
    "videoDuration": 6.633
  },
  {
    "type": "Video",
    "caption": "#AVerdadeDosFatos",
    "hashtags": [
      "AVerdadeDosFatos"
    ],
    "mentions": [],
    "commentsCount": 7550,
    "likesCount": 51622,
    "videoViewCount": 197078,
    "videoPlayCount": 609520,
    "timestamp": "2024-10-04T02:39:56.000Z",
    "ownerFullName": "Eduardo Braide",
    "ownerUsername": "eduardobraide",
    "videoDuration": 57.833
  },
  {
    "type": "Sidecar",
    "caption": "Documento com Pedido de DUARTE JÚNIOR à Procuradoria da República para que encaminhe pedido de Investigação contra Eduardo Braide. \n\nO que comprova que a investigação que Duarte Júnior diz haver contra mim foi pedida por ele mesmo. \n\n#AVerdadeDosFatos",
    "hashtags": [
      "AVerdadeDosFatos"
    ],
    "mentions": [],
    "commentsCount": 606,
    "likesCount": 8437,
    "timestamp": "2024-10-04T03:09:12.000Z",
    "ownerFullName": "Eduardo Braide",
    "ownerUsername": "eduardobraide"
  },
  {
    "type": "Video",
    "caption": "PROGRAMA RONDA NA RUA COM A GUARDA MUNICIPAL",
    "hashtags": [],
    "mentions": [],
    "commentsCount": 1088,
    "likesCount": 19134,
    "videoViewCount": 81287,
    "videoPlayCount": 222651,
    "timestamp": "2024-10-04T04:31:51.000Z",
    "ownerFullName": "Eduardo Braide",
    "ownerUsername": "eduardobraide",
    "videoDuration": 74.866
  },
  {
    "type": "Video",
    "caption": "É mais que trabalho, é cuidar das pessoas! 💙\n\n#AVerdadeDosFatos",
    "hashtags": [
      "AVerdadeDosFatos"
    ],
    "mentions": [],
    "commentsCount": 5157,
    "likesCount": 44801,
    "videoViewCount": 157248,
    "videoPlayCount": 445242,
    "timestamp": "2024-10-04T02:10:15.000Z",
    "ownerFullName": "Eduardo Braide",
    "ownerUsername": "eduardobraide",
    "videoDuration": 56
  },
  {
    "type": "Video",
    "caption": "#AVerdadeDosFatos",
    "hashtags": [
      "AVerdadeDosFatos"
    ],
    "mentions": [],
    "commentsCount": 3303,
    "likesCount": 35395,
    "videoViewCount": 122978,
    "videoPlayCount": 371134,
    "timestamp": "2024-10-04T02:25:26.000Z",
    "ownerFullName": "Eduardo Braide",
    "ownerUsername": "eduardobraide",
    "videoDuration": 70.666
  },
  {
    "type": "Sidecar",
    "caption": "Este é o documento que comprova a ação de Duarte Júnior para SUSPENDER a merenda escolar das crianças de São Luís. \n\nSe esse pedido desumano de Duarte Júnior tivesse sido aceito, mais de 85 mil crianças ficariam sem alimentação escolar nas escolas de São Luís. Mas o Tribunal arquivou a ação de Duarte por ausência de irregularidades. \n\n#AVerdadeDosFatos",
    "hashtags": [
      "AVerdadeDosFatos"
    ],
    "mentions": [],
    "commentsCount": 2439,
    "likesCount": 17432,
    "timestamp": "2024-10-04T02:04:34.000Z",
    "ownerFullName": "Eduardo Braide",
    "ownerUsername": "eduardobraide"
  },
  {
    "type": "Video",
    "caption": "",
    "hashtags": [],
    "mentions": [],
    "commentsCount": 1253,
    "likesCount": 21109,
    "videoViewCount": 70336,
    "videoPlayCount": 190075,
    "timestamp": "2024-10-04T03:38:30.000Z",
    "ownerFullName": "Eduardo Braide",
    "ownerUsername": "eduardobraide",
    "videoDuration": 90.033
  },
  {
    "type": "Video",
    "caption": "",
    "hashtags": [],
    "mentions": [],
    "commentsCount": 3010,
    "likesCount": 25955,
    "videoViewCount": 102945,
    "videoPlayCount": 297218,
    "timestamp": "2024-10-04T04:17:40.000Z",
    "ownerFullName": "Eduardo Braide",
    "ownerUsername": "eduardobraide",
    "videoDuration": 85.766
  },
  {
    "type": "Video",
    "caption": "#AVerdadeDosFatos",
    "hashtags": [
      "AVerdadeDosFatos"
    ],
    "mentions": [],
    "commentsCount": 2320,
    "likesCount": 25188,
    "videoViewCount": 89485,
    "videoPlayCount": 277595,
    "timestamp": "2024-10-04T02:52:11.000Z",
    "ownerFullName": "Eduardo Braide",
    "ownerUsername": "eduardobraide",
    "videoDuration": 25.133
  },
  {
    "type": "Image",
    "caption": "Além de entrar com pedidos de investigação só para ter certidão e postar na rede social, Duarte Júnior também posta investigação que já foi arquivada por não terem encontrado nenhuma irregularidade como se fosse uma investigação em andamento. \n\nEnquanto aqui é trabalho sem parar, com Duarte é mentira sem parar.",
    "hashtags": [],
    "mentions": [],
    "commentsCount": 1081,
    "likesCount": 17631,
    "timestamp": "2024-10-04T03:19:57.000Z",
    "ownerFullName": "Eduardo Braide",
    "ownerUsername": "eduardobraide"
  },
  {
    "type": "Video",
    "caption": "#AVerdadeDosFatos",
    "hashtags": [
      "AVerdadeDosFatos"
    ],
    "mentions": [],
    "commentsCount": 3013,
    "likesCount": 22050,
    "videoViewCount": 146530,
    "videoPlayCount": 590165,
    "timestamp": "2024-10-04T02:23:40.000Z",
    "ownerFullName": "Eduardo Braide",
    "ownerUsername": "eduardobraide",
    "videoDuration": 7.633
  },
  {
    "type": "Video",
    "caption": "RESIDENCIAL MATO GROSSO",
    "hashtags": [],
    "mentions": [],
    "commentsCount": 1085,
    "likesCount": 19394,
    "videoViewCount": 63014,
    "videoPlayCount": 171766,
    "timestamp": "2024-10-04T05:07:17.000Z",
    "ownerFullName": "Eduardo Braide",
    "ownerUsername": "eduardobraide",
    "videoDuration": 88.1
  },
  {
    "type": "Image",
    "caption": "Junto com @eduardobraide, na sede da TV Mirante, para o debate de hoje. Deus te abençoe, meu amor! Estamos juntos! 🙏🏼💙",
    "hashtags": [],
    "mentions": [
      "eduardobraide,"
    ],
    "commentsCount": 2581,
    "likesCount": 33196,
    "timestamp": "2024-10-04T00:20:02.000Z",
    "ownerFullName": "Dra. Graziela Braide",
    "ownerUsername": "graziela_braide"
  },
  {
    "type": "Video",
    "caption": "📺 Hoje é dia de debate! Às 22h estarei ao vivo no debate da TV Mirante falando das transformações que já fizemos na nossa São Luís e tudo o que ainda iremos fazer. \n\nAcompanhem aí, meu povo! É 55 de 💙!\n\n#ÉTrabalhoSemParar #55PraNãoParar #ÉBraide55",
    "hashtags": [
      "ÉTrabalhoSemParar",
      "55PraNãoParar",
      "ÉBraide55"
    ],
    "mentions": [],
    "commentsCount": 1266,
    "likesCount": 10878,
    "videoViewCount": 55109,
    "videoPlayCount": 224823,
    "timestamp": "2024-10-03T16:37:00.000Z",
    "ownerFullName": "Eduardo Braide",
    "ownerUsername": "eduardobraide",
    "videoDuration": 20.013
  },
  {
    "type": "Video",
    "caption": "🤩 Carreata na Zona Rural é diferenciada! Fizeram churrasco e salada de frutas pro prefeito de vocês. Muito obrigado por tanto carinho e apoio, minha Zona Rural! \n\nEu 💙 vocês!",
    "hashtags": [],
    "mentions": [],
    "commentsCount": 913,
    "likesCount": 14690,
    "videoViewCount": 80969,
    "videoPlayCount": 206967,
    "timestamp": "2024-09-30T11:13:40.000Z",
    "ownerFullName": "Eduardo Braide",
    "ownerUsername": "eduardobraide",
    "videoDuration": 43.56
  },
  {
    "type": "Video",
    "caption": "🏘️O sonho da casa própria e toda estrutura pra viver, tá virando realidade para 3.000 famílias: o Residencial Mato Grosso já está na fase final!\n\n#ÉTrabalhoSemParar #55PraNãoParar #ÉBraide55",
    "hashtags": [
      "ÉTrabalhoSemParar",
      "55PraNãoParar",
      "ÉBraide55"
    ],
    "mentions": [],
    "commentsCount": 415,
    "likesCount": 6772,
    "videoViewCount": 31167,
    "videoPlayCount": 266452,
    "timestamp": "2024-10-02T15:44:06.000Z",
    "ownerFullName": "Eduardo Braide",
    "ownerUsername": "eduardobraide",
    "videoDuration": 30.166
  },
  {
    "type": "Video",
    "caption": "😎✨Coloca o óculos escuro, porque lá vem iluminação de LED: Ipase de cima, Ipase de baixo, Maranhão Novo e Vicente Fialho! \n\nAqui tem é trabalho e compromisso com a nossa gente!💙 💪🏽\n\n#BraideTrabalha #PrefeitoPresente",
    "hashtags": [
      "BraideTrabalha",
      "PrefeitoPresente"
    ],
    "mentions": [],
    "commentsCount": 558,
    "likesCount": 6763,
    "videoViewCount": 28255,
    "videoPlayCount": 88608,
    "timestamp": "2024-10-01T15:59:09.000Z",
    "ownerFullName": "Eduardo Braide",
    "ownerUsername": "eduardobraide",
    "videoDuration": 27.466
  },
  {
    "type": "Video",
    "caption": "✨ O boa noite de hoje vem diretamente da casa e do 💙 de vocês: é com 5️⃣5️⃣! Gratidão, meu povo!\n\n#ÉTrabalhoSemParar #55PraNãoParar #ÉBraide55",
    "hashtags": [
      "ÉTrabalhoSemParar",
      "55PraNãoParar",
      "ÉBraide55"
    ],
    "mentions": [],
    "commentsCount": 1481,
    "likesCount": 16972,
    "videoViewCount": 69413,
    "videoPlayCount": 268150,
    "timestamp": "2024-09-30T22:05:42.000Z",
    "ownerFullName": "Eduardo Braide",
    "ownerUsername": "eduardobraide",
    "videoDuration": 8.666
  },
  {
    "type": "Video",
    "caption": "🏥Propostas para a saúde:\n\n✅ Centro de Diagnóstico Municipal para zerar a fila de exames;\n✅ Programa Hora Extra da Saúde;\n✅ Maternidade da Cidade;\n✅ Novo Socorrão II (obra já em andamento;\n✅ Construir + 15 UBS.\n\nSão Luís vai avançar muito mais! 💙💪🏽\n\n#ÉTrabalhoSemParar #55PraNãoParar #ÉBraide55",
    "hashtags": [
      "ÉTrabalhoSemParar",
      "55PraNãoParar",
      "ÉBraide55"
    ],
    "mentions": [],
    "commentsCount": 159,
    "likesCount": 3717,
    "videoViewCount": 14993,
    "videoPlayCount": 54690,
    "timestamp": "2024-10-02T13:01:30.000Z",
    "ownerFullName": "Eduardo Braide",
    "ownerUsername": "eduardobraide",
    "videoDuration": 141.875
  },
  {
    "type": "Image",
    "caption": "",
    "hashtags": [],
    "mentions": [],
    "commentsCount": 572,
    "likesCount": 9730,
    "timestamp": "2024-10-01T20:02:57.000Z",
    "ownerFullName": "Eduardo Braide",
    "ownerUsername": "eduardobraide"
  },
  {
    "type": "Video",
    "caption": "👮🏽‍♀👮🏼‍♂️Propostas para a Segurança:\n\n✅ 100% da cidade com iluminação de LED;\n✅ Central de Segurança com Câmeras Inteligentes;\n✅ Programa Ronda na Rua com a Guarda Municipal.\n\nÉ mais que trabalho, é cuidar das pessoas! 💙\n\n#ÉTrabalhoSemParar #55PraNãoParar #ÉBraide55",
    "hashtags": [
      "ÉTrabalhoSemParar",
      "55PraNãoParar",
      "ÉBraide55"
    ],
    "mentions": [],
    "commentsCount": 326,
    "likesCount": -1,
    "videoViewCount": 20597,
    "videoPlayCount": 71157,
    "timestamp": "2024-10-01T13:27:30.000Z",
    "ownerFullName": "Eduardo Braide",
    "ownerUsername": "eduardobraide",
    "videoDuration": 146.168
  },
  {
    "type": "Video",
    "caption": "O 5️⃣5️⃣ tá no 💙 do Santo Antônio, Pirapora, Residencial João Alberto, Vila Lobão, Jardim Conceição, João de Deus, Residencial Santos Dumont e São Cristóvão.\n\nSerão + 4 anos de muito trabalho pela nossa gente e pela transformação da nossa cidade. Pra cima, minha São Luís! 🤩\n\n#ÉTrabalhoSemParar #55PraNãoParar #ÉBraide55",
    "hashtags": [
      "ÉTrabalhoSemParar",
      "55PraNãoParar",
      "ÉBraide55"
    ],
    "mentions": [],
    "commentsCount": 314,
    "likesCount": 6105,
    "videoViewCount": 26486,
    "videoPlayCount": 80665,
    "timestamp": "2024-10-01T09:51:20.000Z",
    "ownerFullName": "Eduardo Braide",
    "ownerUsername": "eduardobraide",
    "videoDuration": 43.958
  },
  {
    "type": "Video",
    "caption": "👷🏼‍♂️ Alôô, Bairro de Fátima! Alôô, Rua do Buraco Cheiroso, Paulo Frontin e Rua do Chafariz: o sofrimento e incômodo de + de 40 anos com alagamentos acabou! \n\n🚧 Fizemos todas as obras de drenagem profunda necessária e já estamos na fase final do asfalto novo. \n\nEstamos chegando também minha Rua do Peixe e Travessa Kennedy. Meu BF do ❤️ tá ficando é lindo!\n\n#BraideTrabalha #PrefeitoPresente",
    "hashtags": [
      "BraideTrabalha",
      "PrefeitoPresente"
    ],
    "mentions": [],
    "commentsCount": 1804,
    "likesCount": 15831,
    "videoViewCount": 67973,
    "videoPlayCount": 186870,
    "timestamp": "2024-10-02T16:28:42.000Z",
    "ownerFullName": "Eduardo Braide",
    "ownerUsername": "eduardobraide",
    "videoDuration": 59.933
  },
  {
    "type": "Video",
    "caption": "É bom demais ser recebido por vocês com todo esse carinho, meu povo da Vila Itamar e Vila Esperança! 5️⃣5️⃣💙\n\nE tamo chegando também, vilas Sarney, Nova República, Industrial e Samara, Rio Grande, Pedrinhas, Inhaúma, Coqueiro e Estiva.🤩",
    "hashtags": [],
    "mentions": [],
    "commentsCount": 350,
    "likesCount": 8163,
    "videoViewCount": 58246,
    "videoPlayCount": 230108,
    "timestamp": "2024-09-29T14:30:30.000Z",
    "ownerFullName": "Eduardo Braide",
    "ownerUsername": "eduardobraide",
    "videoDuration": 17.833
  },
  {
    "type": "Video",
    "caption": "📄🖊️Compromissos para o nosso segundo mandato:\n\n✅ Maternidade da Cidade com 100 leitos;\n✅ Construção de + 15 UBS;\n✅ Criação do Diagnocentro;\n✅ Programa Hora Extra da Saúde.\n\nSão Luís vai avançar muito mais! 💙💪🏽\n\n#ÉTrabalhoSemParar #55PraNãoParar #ÉBraide55",
    "hashtags": [
      "ÉTrabalhoSemParar",
      "55PraNãoParar",
      "ÉBraide55"
    ],
    "mentions": [],
    "commentsCount": 239,
    "likesCount": 4389,
    "videoViewCount": 15276,
    "videoPlayCount": 65917,
    "timestamp": "2024-09-27T11:27:44.000Z",
    "ownerFullName": "Eduardo Braide",
    "ownerUsername": "eduardobraide",
    "videoDuration": 143.458
  },
  {
    "type": "Sidecar",
    "caption": "📸🤩 Segura esses registros da nossa carreata nos jardins São Cristóvão 1 e 2, IPEM São Cristóvão, Cohapam, São Bernardo, Vila Brasil e Forquilha. \n\nFoi lindo demais receber todo esse carinho de vocês, meu povo! É 55 de 💙!\n\nAgora é na Vila Itamar e região. Simboraa! 😎\n\n#ÉTrabalhoSemParar #55PraNãoParar #ÉBraide55",
    "hashtags": [
      "ÉTrabalhoSemParar",
      "55PraNãoParar",
      "ÉBraide55"
    ],
    "mentions": [],
    "commentsCount": 472,
    "likesCount": 13485,
    "timestamp": "2024-09-29T12:19:34.000Z",
    "ownerFullName": "Eduardo Braide",
    "ownerUsername": "eduardobraide"
  },
  {
    "type": "Video",
    "caption": "O que foi isso minha Alemanha! 😍💙",
    "hashtags": [],
    "mentions": [],
    "commentsCount": 948,
    "likesCount": 11698,
    "videoViewCount": 56267,
    "videoPlayCount": 132372,
    "timestamp": "2024-09-27T00:24:59.000Z",
    "ownerFullName": "Eduardo Braide",
    "ownerUsername": "eduardobraide",
    "videoDuration": 876.881
  },
  {
    "type": "Video",
    "caption": "🌊😎 A onda do 5️⃣5️⃣ tomou conta do meu país Cidade Operária e região! \n\nMeu coração é só alegria! Foi lindo demais! Muito obrigado a cada um de vocês que estiveram presentes! 💙\n\n#ÉTrabalhoSemParar #55PraNãoParar #ÉBraide55",
    "hashtags": [
      "ÉTrabalhoSemParar",
      "55PraNãoParar",
      "ÉBraide55"
    ],
    "mentions": [],
    "commentsCount": 550,
    "likesCount": 6749,
    "videoViewCount": 27341,
    "videoPlayCount": 83434,
    "timestamp": "2024-09-25T05:42:48.000Z",
    "ownerFullName": "Eduardo Braide",
    "ownerUsername": "eduardobraide",
    "videoDuration": 71.666
  },
  {
    "type": "Video",
    "caption": "✅ Mais uma pesquisa nacional confirma a vontade do povo e que a transformação da nossa cidade não vai parar: é primeiro turno! \n\nObrigado, Deus! Obrigado, minha São Luís! 🙌🏽💙\n\n#ÉTrabalhoSemParar #55PraNãoParar #ÉBraide55",
    "hashtags": [
      "ÉTrabalhoSemParar",
      "55PraNãoParar",
      "ÉBraide55"
    ],
    "mentions": [],
    "commentsCount": 2565,
    "likesCount": 20715,
    "videoViewCount": 89293,
    "videoPlayCount": 321554,
    "timestamp": "2024-09-28T00:13:33.000Z",
    "ownerFullName": "Eduardo Braide",
    "ownerUsername": "eduardobraide",
    "videoDuration": 32.019
  },
  {
    "type": "Video",
    "caption": "✅ Depois da iluminação de Led no Retiro Natal e Vila Passos, olha o asfalto novo chegando!\n\n🛣️ São 5cm de espessura do asfalto com brita pra garantir a qualidade e durabilidade da obra.\n\nPor aqui já sabe, né? A fiscalização e o trabalho não param! 💪🏽💙\n\n#BraideTrabalha #PrefeitoPresente",
    "hashtags": [
      "BraideTrabalha",
      "PrefeitoPresente"
    ],
    "mentions": [],
    "commentsCount": 419,
    "likesCount": 6244,
    "videoViewCount": 27887,
    "videoPlayCount": 86946,
    "timestamp": "2024-09-25T17:27:12.000Z",
    "ownerFullName": "Eduardo Braide",
    "ownerUsername": "eduardobraide",
    "videoDuration": 22.9
  },
  {
    "type": "Video",
    "caption": "A 🌊 do 5️⃣5️⃣ tomou conta da Vila Embratel! 💙",
    "hashtags": [],
    "mentions": [],
    "commentsCount": 1000,
    "likesCount": 9823,
    "videoViewCount": 32652,
    "videoPlayCount": 93648,
    "timestamp": "2024-09-28T00:22:31.000Z",
    "ownerFullName": "Eduardo Braide",
    "ownerUsername": "eduardobraide",
    "videoDuration": 1047.111
  },
  {
    "type": "Video",
    "caption": "Foi suquinho gourmet e eu posso provar, @portalmarrapa! 🤣\n\n@suquinhogourmetdamigles do Recanto Verde: o melhor de São Luís!😋",
    "hashtags": [],
    "mentions": [
      "portalmarrapa!",
      "suquinhogourmetdamigles"
    ],
    "commentsCount": 552,
    "likesCount": 11895,
    "videoViewCount": 60067,
    "videoPlayCount": 159103,
    "timestamp": "2024-09-26T02:23:55.000Z",
    "ownerFullName": "Eduardo Braide",
    "ownerUsername": "eduardobraide",
    "videoDuration": 42.701
  },
  {
    "type": "Video",
    "caption": "📺 Quinta-feira que vem vou dar uma pausa nos trabalhos, porque eu espero vocês às 22h no debate da Globo. 💙💪🏽",
    "hashtags": [],
    "mentions": [],
    "commentsCount": 1909,
    "likesCount": 19515,
    "videoViewCount": 73674,
    "videoPlayCount": 214501,
    "timestamp": "2024-09-26T12:12:47.000Z",
    "ownerFullName": "Eduardo Braide",
    "ownerUsername": "eduardobraide",
    "videoDuration": 37.791
  },
  {
    "type": "Video",
    "caption": "Alôô, minha Área Itaqui-Bacanga: a 🌊 do 5️⃣5️⃣ já chegou!",
    "hashtags": [],
    "mentions": [],
    "commentsCount": 950,
    "likesCount": 11390,
    "videoViewCount": 42943,
    "videoPlayCount": 115720,
    "timestamp": "2024-09-25T23:05:40.000Z",
    "ownerFullName": "Eduardo Braide",
    "ownerUsername": "eduardobraide",
    "videoDuration": 860.334
  },
  {
    "type": "Video",
    "caption": "🏥🤩 Anotem aí: dia 15 de outubro a Zona Rural vai ganhar seu tão sonhado Hospital! \n\nEstamos fazendo o que nunca foi feito por São Luís e vamos fazer muito mais! 💪🏽💙\n\n#BraideTrabalha #PrefeitoPresente",
    "hashtags": [
      "BraideTrabalha",
      "PrefeitoPresente"
    ],
    "mentions": [],
    "commentsCount": 1635,
    "likesCount": 14210,
    "videoViewCount": 52800,
    "videoPlayCount": 180567,
    "timestamp": "2024-09-27T15:12:52.000Z",
    "ownerFullName": "Eduardo Braide",
    "ownerUsername": "eduardobraide",
    "videoDuration": 34.433
  },
  {
    "type": "Video",
    "caption": "A 🌊 do 5️⃣5️⃣ tomou conta da Cidade Olímpica!",
    "hashtags": [],
    "mentions": [],
    "commentsCount": 610,
    "likesCount": 9564,
    "videoViewCount": 29377,
    "videoPlayCount": 80518,
    "timestamp": "2024-09-23T21:56:31.000Z",
    "ownerFullName": "Eduardo Braide",
    "ownerUsername": "eduardobraide",
    "videoDuration": 906.17
  },
  {
    "type": "Video",
    "caption": "✅ + 20 CRECHES DE TEMPO INTEGRAL\n\n#ÉTrabalhoSemParar #55PraNãoParar #ÉBraide55",
    "hashtags": [
      "ÉTrabalhoSemParar",
      "55PraNãoParar",
      "ÉBraide55"
    ],
    "mentions": [],
    "commentsCount": 128,
    "likesCount": 1986,
    "videoViewCount": 7287,
    "videoPlayCount": 28163,
    "timestamp": "2024-09-23T21:59:35.000Z",
    "ownerFullName": "Eduardo Braide",
    "ownerUsername": "eduardobraide",
    "videoDuration": 106.233
  },
  {
    "type": "Video",
    "caption": "✅ PARCERIA COM O UNICEF\n\n#ÉTrabalhoSemParar #55PraNãoParar #ÉBraide55",
    "hashtags": [
      "ÉTrabalhoSemParar",
      "55PraNãoParar",
      "ÉBraide55"
    ],
    "mentions": [],
    "commentsCount": 51,
    "likesCount": 1494,
    "videoViewCount": 6057,
    "videoPlayCount": 25368,
    "timestamp": "2024-09-24T02:28:19.000Z",
    "ownerFullName": "Eduardo Braide",
    "ownerUsername": "eduardobraide",
    "videoDuration": 68.033
  },
  {
    "type": "Video",
    "caption": "✅ O CENTRO DE ESPECIALIDADES DEU CERTO!\n\n#ÉTrabalhoSemParar #55PraNãoParar #ÉBraide55",
    "hashtags": [
      "ÉTrabalhoSemParar",
      "55PraNãoParar",
      "ÉBraide55"
    ],
    "mentions": [],
    "commentsCount": 176,
    "likesCount": 2795,
    "videoViewCount": 12281,
    "videoPlayCount": 42637,
    "timestamp": "2024-09-24T01:35:32.000Z",
    "ownerFullName": "Eduardo Braide",
    "ownerUsername": "eduardobraide",
    "videoDuration": 123.766
  },
  {
    "type": "Video",
    "caption": "✅ NOTA A EM TRANSPARÊNCIA!\n\n#ÉTrabalhoSemParar #55PraNãoParar #ÉBraide55",
    "hashtags": [
      "ÉTrabalhoSemParar",
      "55PraNãoParar",
      "ÉBraide55"
    ],
    "mentions": [],
    "commentsCount": 206,
    "likesCount": 2847,
    "videoViewCount": 12976,
    "videoPlayCount": 46075,
    "timestamp": "2024-09-23T21:02:04.000Z",
    "ownerFullName": "Eduardo Braide",
    "ownerUsername": "eduardobraide",
    "videoDuration": 68.9
  },
  {
    "type": "Video",
    "caption": "MINISTÉRIO PÚBLICO COMPROVA REGULARIDADE DE CONTRATOS.\n\n#ÉTrabalhoSemParar #55PraNãoParar #ÉBraide55",
    "hashtags": [
      "ÉTrabalhoSemParar",
      "55PraNãoParar",
      "ÉBraide55"
    ],
    "mentions": [],
    "commentsCount": 131,
    "likesCount": 2226,
    "videoViewCount": 12343,
    "videoPlayCount": 42149,
    "timestamp": "2024-09-24T10:37:29.000Z",
    "ownerFullName": "Eduardo Braide",
    "ownerUsername": "eduardobraide",
    "videoDuration": 75.933
  },
  {
    "type": "Video",
    "caption": "✅ MAIS CONCURSOS E CARREIRAS MELHORES!\n\n#ÉTrabalhoSemParar #55PraNãoParar #ÉBraide55",
    "hashtags": [
      "ÉTrabalhoSemParar",
      "55PraNãoParar",
      "ÉBraide55"
    ],
    "mentions": [],
    "commentsCount": 108,
    "likesCount": 2049,
    "videoViewCount": 8310,
    "videoPlayCount": 31211,
    "timestamp": "2024-09-23T21:25:35.000Z",
    "ownerFullName": "Eduardo Braide",
    "ownerUsername": "eduardobraide",
    "videoDuration": 89.1
  },
  {
    "type": "Video",
    "caption": "✅ TRABALHO SEM PARAR\n\n#ÉTrabalhoSemParar #55PraNãoParar #ÉBraide55",
    "hashtags": [
      "ÉTrabalhoSemParar",
      "55PraNãoParar",
      "ÉBraide55"
    ],
    "mentions": [],
    "commentsCount": 479,
    "likesCount": 4553,
    "videoViewCount": 14504,
    "videoPlayCount": 49572,
    "timestamp": "2024-09-24T12:44:34.000Z",
    "ownerFullName": "Eduardo Braide",
    "ownerUsername": "eduardobraide",
    "videoDuration": 84.6
  },
  {
    "type": "Video",
    "caption": "🤩☕ O melhor café de São Luís fica na Cidade Olímpica e eu posso provar, meu povo! \n\nSepara meu café com bolo de tapioca, que eu tô chegando aí, Dona Ana.💙\n\nVia: @cid.olimpica_oficial",
    "hashtags": [],
    "mentions": [
      "cid.olimpica_oficial"
    ],
    "commentsCount": 697,
    "likesCount": 8157,
    "videoViewCount": 38763,
    "videoPlayCount": 109250,
    "timestamp": "2024-09-24T18:42:45.000Z",
    "ownerFullName": "Eduardo Braide",
    "ownerUsername": "eduardobraide",
    "videoDuration": 59.119
  },
  {
    "type": "Video",
    "caption": "Não tem jeito, é impossível não amar o prefeito do povo 💙\n\nÉ 5️⃣5️⃣ pro trabalho continuar, é @eduardobraide pra São Luís seguir avançando! 🫶🏻\n\n#Braide55",
    "hashtags": [
      "Braide55"
    ],
    "mentions": [
      "eduardobraide"
    ],
    "commentsCount": 304,
    "likesCount": 4518,
    "videoViewCount": 26339,
    "videoPlayCount": 71655,
    "timestamp": "2024-09-24T22:00:00.000Z",
    "ownerFullName": "Dra. Graziela Braide",
    "ownerUsername": "graziela_braide",
    "videoDuration": 11.98
  },
  {
    "type": "Video",
    "caption": "✅ 1ª MATERNIDADE MUNICIPAL\n\n#ÉTrabalhoSemParar #55PraNãoParar #ÉBraide55",
    "hashtags": [
      "ÉTrabalhoSemParar",
      "55PraNãoParar",
      "ÉBraide55"
    ],
    "mentions": [],
    "commentsCount": 136,
    "likesCount": 2824,
    "videoViewCount": 15243,
    "videoPlayCount": 51274,
    "timestamp": "2024-09-23T23:02:50.000Z",
    "ownerFullName": "Eduardo Braide",
    "ownerUsername": "eduardobraide",
    "videoDuration": 65.366
  },
  {
    "type": "Video",
    "caption": "QUEM NÃO DEVE, NÃO TEME! \n\n#ÉTrabalhoSemParar #55PraNãoParar #ÉBraide55",
    "hashtags": [
      "ÉTrabalhoSemParar",
      "55PraNãoParar",
      "ÉBraide55"
    ],
    "mentions": [],
    "commentsCount": 1378,
    "likesCount": 15013,
    "videoViewCount": 82239,
    "videoPlayCount": 228471,
    "timestamp": "2024-09-24T02:01:55.000Z",
    "ownerFullName": "Eduardo Braide",
    "ownerUsername": "eduardobraide",
    "videoDuration": 49.2
  },
  {
    "type": "Video",
    "caption": "🚶🏽‍➡️Construiremos novas passarelas para garantir maior segurança para os pedestres. \n\n#ÉTrabalhoSemParar #55PraNãoParar #ÉBraide55",
    "hashtags": [
      "ÉTrabalhoSemParar",
      "55PraNãoParar",
      "ÉBraide55"
    ],
    "mentions": [],
    "commentsCount": 107,
    "likesCount": 1783,
    "videoViewCount": 8059,
    "videoPlayCount": 30997,
    "timestamp": "2024-09-23T20:35:04.000Z",
    "ownerFullName": "Eduardo Braide",
    "ownerUsername": "eduardobraide",
    "videoDuration": 75.1
  },
  {
    "type": "Video",
    "caption": "#Domingou na carreata mais feliz e animada de São Luís, a do 5️⃣5️⃣ ✌🏻\n\nHoje foi dia de receber o carinho das pessoas nas ruas. Obrigada por tanto apoio nessa caminhada! 🙌🏻\n\nÉ 5️⃣5️⃣ na cabeça e no 💙! \n\n#Braide55 #PrefeitoDoPovo #É55 #ProTrabalhoContinuar",
    "hashtags": [
      "Domingou",
      "Braide55",
      "PrefeitoDoPovo",
      "É55",
      "ProTrabalhoContinuar"
    ],
    "mentions": [],
    "commentsCount": 428,
    "likesCount": 5117,
    "videoViewCount": 25626,
    "videoPlayCount": 67430,
    "timestamp": "2024-09-23T03:20:50.000Z",
    "ownerFullName": "Dra. Graziela Braide",
    "ownerUsername": "graziela_braide",
    "videoDuration": 70.333
  },
  {
    "type": "Video",
    "caption": "⬆️⬇️ Trânsito Livre para todos: pedestres, ciclistas e condutores!\n\n#ÉTrabalhoSemParar #55PraNãoParar #ÉBraide55",
    "hashtags": [
      "ÉTrabalhoSemParar",
      "55PraNãoParar",
      "ÉBraide55"
    ],
    "mentions": [],
    "commentsCount": 240,
    "likesCount": 3243,
    "videoViewCount": 11227,
    "videoPlayCount": 40819,
    "timestamp": "2024-09-23T19:59:12.000Z",
    "ownerFullName": "Eduardo Braide",
    "ownerUsername": "eduardobraide",
    "videoDuration": 109.266
  },
  {
    "type": "Video",
    "caption": "A 🌊 do 5️⃣5️⃣ tá tomando conta dos bairros!\n\nA alegria e o entusiasmo de vocês enchem meu coração de gratidão e também é a confirmação de que o nosso trabalho não pode parar! \n\nO povo é quem manda! Pra cima, São Luís! ❤️💪🏽\n\n#Braide55 #ÉTrabalhoSemParar #SãoLuísÉ55",
    "hashtags": [
      "Braide55",
      "ÉTrabalhoSemParar",
      "SãoLuísÉ55"
    ],
    "mentions": [],
    "commentsCount": 450,
    "likesCount": 7511,
    "videoViewCount": 31277,
    "videoPlayCount": 90564,
    "timestamp": "2024-09-21T03:39:00.000Z",
    "ownerFullName": "Eduardo Braide",
    "ownerUsername": "eduardobraide",
    "videoDuration": 40.38
  },
  {
    "type": "Video",
    "caption": "📣Alôôô, minha Vila Conceição! \n\nO sabadão é com óculos escuros 😎 e, se tem óculos escuros, é porque chegou a iluminação de LED pra noite virar dia! 🌙✨\n\nAh, e já chegou também o asfalto novo pra deixar minha Vila no grau! 🛣️\n\nPor aqui seguimos fazendo por São Luís o que nunca tinha sido feito antes! 💪🏽💙\n\n#BraideTrabalha #PrefeitoPresente",
    "hashtags": [
      "BraideTrabalha",
      "PrefeitoPresente"
    ],
    "mentions": [],
    "commentsCount": 898,
    "likesCount": 11483,
    "videoViewCount": 48991,
    "videoPlayCount": 161203,
    "timestamp": "2024-09-21T14:25:05.000Z",
    "ownerFullName": "Eduardo Braide",
    "ownerUsername": "eduardobraide",
    "videoDuration": 26.633
  },
  {
    "type": "Video",
    "caption": "✅ MOBILIDADE URBANA\n\n#ÉTrabalhoSemParar #55PraNãoParar #ÉBraide55",
    "hashtags": [
      "ÉTrabalhoSemParar",
      "55PraNãoParar",
      "ÉBraide55"
    ],
    "mentions": [],
    "commentsCount": 147,
    "likesCount": 2496,
    "videoViewCount": 9614,
    "videoPlayCount": 35752,
    "timestamp": "2024-09-23T19:35:51.000Z",
    "ownerFullName": "Eduardo Braide",
    "ownerUsername": "eduardobraide",
    "videoDuration": 62.166
  },
  {
    "type": "Image",
    "caption": "#BomDiaDoBraide #BraideTrabalha #PrefeitoPresente",
    "hashtags": [
      "BomDiaDoBraide",
      "BraideTrabalha",
      "PrefeitoPresente"
    ],
    "mentions": [],
    "commentsCount": 567,
    "likesCount": 9799,
    "timestamp": "2024-09-22T10:06:43.000Z",
    "ownerFullName": "Eduardo Braide",
    "ownerUsername": "eduardobraide"
  },
  {
    "type": "Video",
    "caption": "Que energia foi essa, meu Polo Coroadinho? É 5️⃣5️⃣ no 💙.\n\nContem sempre comigo!💪🏽\n\n#Braide55 #ÉTrabalhoSemParar #SãoLuísÉ55",
    "hashtags": [
      "Braide55",
      "ÉTrabalhoSemParar",
      "SãoLuísÉ55"
    ],
    "mentions": [],
    "commentsCount": 934,
    "likesCount": 14002,
    "videoViewCount": 51681,
    "videoPlayCount": 151760,
    "timestamp": "2024-09-22T11:32:51.000Z",
    "ownerFullName": "Eduardo Braide",
    "ownerUsername": "eduardobraide",
    "videoDuration": 78.966
  },
  {
    "type": "Video",
    "caption": "👷🏼‍♂️Alôôô, minha Vila Embratel!\n\nTem Asfalto Novo chegando nas ruas e a partir da semana que vem começa a chegar o LED também! \n\nMinha Embratel tá ficando é 🔝! 💙\n\n#BraideTrabalha #PrefeitoPresente",
    "hashtags": [
      "BraideTrabalha",
      "PrefeitoPresente"
    ],
    "mentions": [],
    "commentsCount": 904,
    "likesCount": 8733,
    "videoViewCount": 39145,
    "videoPlayCount": 126697,
    "timestamp": "2024-09-21T19:24:46.000Z",
    "ownerFullName": "Eduardo Braide",
    "ownerUsername": "eduardobraide",
    "videoDuration": 41.266
  },
  {
    "type": "Video",
    "caption": "💡✨😎 Avisa aí que a turma da Radional, Santa Cruz e Vera Cruz já podem colocar o óculos escuros pra andar à noite, porque vai virar é dia com a iluminação de LED que tá chegando por aqui! \n\nA gente segue fiscalizando nossas obras, serviços e fazendo o que nunca foi feito por São Luís! 💙💪🏽\n\n#BraideTrabalha #PrefeitoPresente",
    "hashtags": [
      "BraideTrabalha",
      "PrefeitoPresente"
    ],
    "mentions": [],
    "commentsCount": 579,
    "likesCount": 6808,
    "videoViewCount": 25211,
    "videoPlayCount": 81803,
    "timestamp": "2024-09-22T16:30:04.000Z",
    "ownerFullName": "Eduardo Braide",
    "ownerUsername": "eduardobraide",
    "videoDuration": 27.266
  },
  {
    "type": "Image",
    "caption": "Esta é a Lista de Projetos do município de São Luís aprovados no novo PAC. Temos parcerias com o Governo Federal no valor de mais de R$ 500 milhões. \n\nJá trabalhamos e continuaremos trabalhando com todos que possam contribuir para melhorar ainda mais a vida da nossa gente.\n\n#AVerdadeDosFatos",
    "hashtags": [
      "AVerdadeDosFatos"
    ],
    "mentions": [],
    "commentsCount": 1026,
    "likesCount": 10811,
    "timestamp": "2024-10-04T01:55:39.000Z",
    "ownerFullName": "Eduardo Braide",
    "ownerUsername": "eduardobraide"
  },
  {
    "type": "Video",
    "caption": "Carreata do 5️⃣5️⃣ no Residencial Amendoeira, Morada do Sol e Santo Antônio! Simboraa! 💙\n\n#Braide55 #ÉTrabalhoSemParar #SãoLuísÉ55",
    "hashtags": [
      "Braide55",
      "ÉTrabalhoSemParar",
      "SãoLuísÉ55"
    ],
    "mentions": [],
    "commentsCount": 528,
    "likesCount": 7564,
    "videoViewCount": 22888,
    "videoPlayCount": 69616,
    "timestamp": "2024-09-22T20:37:12.000Z",
    "ownerFullName": "Eduardo Braide",
    "ownerUsername": "eduardobraide",
    "videoDuration": 976.173
  },
  {
    "type": "Video",
    "caption": "🚍Tem + 300 novos ônibus vindo aí! \n\n#ÉTrabalhoSemParar #55PraNãoParar #ÉBraide55",
    "hashtags": [
      "ÉTrabalhoSemParar",
      "55PraNãoParar",
      "ÉBraide55"
    ],
    "mentions": [],
    "commentsCount": 686,
    "likesCount": 7837,
    "videoViewCount": 32228,
    "videoPlayCount": 98584,
    "timestamp": "2024-09-23T19:00:34.000Z",
    "ownerFullName": "Eduardo Braide",
    "ownerUsername": "eduardobraide",
    "videoDuration": 118.566
  },
  {
    "type": "Video",
    "caption": "🛣️ Elevado da Cidade: o que já está bom, vai ficar ainda melhor! Dá um confere no vídeo aí. 🤩\n\n#BraideTrabalha\n#PrefeitoPresente",
    "hashtags": [
      "BraideTrabalha",
      "PrefeitoPresente"
    ],
    "mentions": [],
    "commentsCount": 1884,
    "likesCount": 21196,
    "videoViewCount": 89690,
    "videoPlayCount": 265151,
    "timestamp": "2024-09-19T14:09:55.000Z",
    "ownerFullName": "Eduardo Braide",
    "ownerUsername": "eduardobraide",
    "videoDuration": 42.005
  },
  {
    "type": "Video",
    "caption": "Minha Cohab do 💙!\n\n🤩Teve abraço, gente fazendo coração da janela, da porta de casa, tinha gente mandando beijo, teve oração e todas as manifestações de carinho e apoio que vocês possam imaginar durante a nossa carreata pela Cohab e região. \n\nMuito obrigado a todos vocês. É 55 de 🫶🏽! \n\n#ÉTrabalhoSemParar #55PraNãoParar #ÉBraide55",
    "hashtags": [
      "ÉTrabalhoSemParar",
      "55PraNãoParar",
      "ÉBraide55"
    ],
    "mentions": [],
    "commentsCount": 507,
    "likesCount": 7151,
    "videoViewCount": 33625,
    "videoPlayCount": 91607,
    "timestamp": "2024-09-18T01:50:34.000Z",
    "ownerFullName": "Eduardo Braide",
    "ownerUsername": "eduardobraide",
    "videoDuration": 59.766
  },
  {
    "type": "Video",
    "caption": "👮🏽‍♂️👮🏻 Estamos reforçando nossa Guarda Municipal para melhorarmos a segurança pública na cidade!\n\nConvocamos mais agentes e entregamos armamentos novos. 💪🏽\n\n#BraideTrabalha #PrefeitoPresente",
    "hashtags": [
      "BraideTrabalha",
      "PrefeitoPresente"
    ],
    "mentions": [],
    "commentsCount": 1173,
    "likesCount": 16389,
    "videoViewCount": 68126,
    "videoPlayCount": 200148,
    "timestamp": "2024-09-20T14:40:54.000Z",
    "ownerFullName": "Eduardo Braide",
    "ownerUsername": "eduardobraide",
    "videoDuration": 41.366
  },
  {
    "type": "Video",
    "caption": "🚧 Alô minha Área Itaqui-Bacanga, fiscalizei a chegada do Asfalto Novo + LED na Vila Dom Luís!\n\n✅ Depois de + de 30 anos de espera, olha o asfalto novo e britado chegando nas ruas do bairro.\n\nSeguimos fazendo o que nunca foi feito antes! Simboraa!💙💪🏽\n\n#BraideTrabalha #PrefeitoPresente",
    "hashtags": [
      "BraideTrabalha",
      "PrefeitoPresente"
    ],
    "mentions": [],
    "commentsCount": 526,
    "likesCount": 6717,
    "videoViewCount": 33124,
    "videoPlayCount": 93492,
    "timestamp": "2024-09-17T17:19:11.000Z",
    "ownerFullName": "Eduardo Braide",
    "ownerUsername": "eduardobraide",
    "videoDuration": 29.4
  },
  {
    "type": "Video",
    "caption": "🏘️ Notícia boa para os futuros moradores do Residencial Mato Grosso! \n\n#BraideTrabalha #PrefeitoPresente",
    "hashtags": [
      "BraideTrabalha",
      "PrefeitoPresente"
    ],
    "mentions": [],
    "commentsCount": 1491,
    "likesCount": 23020,
    "videoViewCount": 116536,
    "videoPlayCount": 357264,
    "timestamp": "2024-09-17T14:32:20.000Z",
    "ownerFullName": "Eduardo Braide",
    "ownerUsername": "eduardobraide",
    "videoDuration": 38.033
  },
  {
    "type": "Video",
    "caption": "🌟 O povo de São Luís disse e quer @eduardobraide de novo para o trabalho continuar! 💙\n\nO reconhecimento de vocês é o combustível pra seguir com mais força nessa campanha por uma São Luís cada vez melhor! 🥰\n\nObrigada Coroado, João Paulo, BF, Retiro Natal e Monte Castelo pelo carinho e recepção em mais uma carreata do 5️⃣5️⃣! Foi lindo! 🫶🏻\n\n#ÉBraideDeNovo #Braide55 #ProTrabalhoContinuar #BraidePrefeito",
    "hashtags": [
      "ÉBraideDeNovo",
      "Braide55",
      "ProTrabalhoContinuar",
      "BraidePrefeito"
    ],
    "mentions": [
      "eduardobraide"
    ],
    "commentsCount": 730,
    "likesCount": 11509,
    "videoViewCount": 57097,
    "videoPlayCount": 149030,
    "timestamp": "2024-09-19T03:05:30.000Z",
    "ownerFullName": "Dra. Graziela Braide",
    "ownerUsername": "graziela_braide",
    "videoDuration": 82.267
  },
  {
    "type": "Video",
    "caption": "🏥 Você não vai mais precisar faltar ao trabalho pra ter atendimento: vamos ter o HORA EXTRA DA SAÚDE! \n\n✅ UBS funcionarão até às 19h e aos sábados;\n\n✅ Clinícas da Família abrirão aos sábados;\n\nÉ mais que trabalho, é cuidar das pessoas! 💙\n\n#ÉTrabalhoSemParar #55PraNãoParar #ÉBraide55",
    "hashtags": [
      "ÉTrabalhoSemParar",
      "55PraNãoParar",
      "ÉBraide55"
    ],
    "mentions": [],
    "commentsCount": 173,
    "likesCount": 2824,
    "videoViewCount": 13901,
    "videoPlayCount": 56055,
    "timestamp": "2024-09-18T10:04:48.000Z",
    "ownerFullName": "Eduardo Braide",
    "ownerUsername": "eduardobraide",
    "videoDuration": 30.066
  },
  {
    "type": "Video",
    "caption": "👀 Fiscalizando a instalação do LED que vai chegar em toda área Itaqui-Bacanga! \n\nAqui #ÉTrabalhoSemParar 💪🏽",
    "hashtags": [
      "ÉTrabalhoSemParar"
    ],
    "mentions": [],
    "commentsCount": 1642,
    "likesCount": 15503,
    "videoViewCount": 65959,
    "videoPlayCount": 206560,
    "timestamp": "2024-09-20T02:36:20.000Z",
    "ownerFullName": "Eduardo Braide",
    "ownerUsername": "eduardobraide",
    "videoDuration": 38.567
  },
  {
    "type": "Video",
    "caption": "Alguém me acompanha na dancinha do 5️⃣5️⃣ aí? 🤣💙",
    "hashtags": [],
    "mentions": [],
    "commentsCount": 701,
    "likesCount": 9459,
    "videoViewCount": 51973,
    "videoPlayCount": 153945,
    "timestamp": "2024-09-20T21:07:11.000Z",
    "ownerFullName": "Eduardo Braide",
    "ownerUsername": "eduardobraide",
    "videoDuration": 14.1
  },
  {
    "type": "Video",
    "caption": "😎 Alôôô, meu país Cidade Operária: se eu tô de óculos escuro, é porque o LED chegou na área! \n\n✨ Tô fiscalizando o serviço e a boa notícia é que até neste domingo (22), TODAS as ruas do meu país C.O. estarão com a nova iluminação! 🤩\n\n#BraideTrabalha\n#PrefeitoPresente",
    "hashtags": [
      "BraideTrabalha",
      "PrefeitoPresente"
    ],
    "mentions": [],
    "commentsCount": 1664,
    "likesCount": 15658,
    "videoViewCount": 62109,
    "videoPlayCount": 173771,
    "timestamp": "2024-09-18T16:33:18.000Z",
    "ownerFullName": "Eduardo Braide",
    "ownerUsername": "eduardobraide",
    "videoDuration": 42.766
  },
  {
    "type": "Video",
    "caption": "A carreata que virou caminhada! 5️⃣5️⃣💙",
    "hashtags": [],
    "mentions": [],
    "commentsCount": 1683,
    "likesCount": 20446,
    "videoViewCount": 83594,
    "videoPlayCount": 205232,
    "timestamp": "2024-09-21T00:36:32.000Z",
    "ownerFullName": "Eduardo Braide",
    "ownerUsername": "eduardobraide",
    "videoDuration": 525.944
  },
  {
    "type": "Video",
    "caption": "Carreata do 5️⃣5️⃣ no Coroado! 💙",
    "hashtags": [],
    "mentions": [],
    "commentsCount": 799,
    "likesCount": 8258,
    "videoViewCount": 22743,
    "videoPlayCount": 68924,
    "timestamp": "2024-09-18T21:54:25.000Z",
    "ownerFullName": "Eduardo Braide",
    "ownerUsername": "eduardobraide",
    "videoDuration": 1268.552
  },
  {
    "type": "Video",
    "caption": "🤩 Já fizemos muito, mas vamos fazer muito mais:\n\n✅ Na segurança, o Programa Ronda na Rua;\n\n✅ Na educação, mais 20 Creches de Tempo Integral;\n\n✅ Na saúde, o Programa Hora Extra da Saúde;\n\n✅ E vamos construir a tão sonhada Maternidade da Cidade.\n\nNa hora de votar, é 5️⃣5️⃣ pro trabalho não parar! 💙\n\n#ÉTrabalhoSemParar #55PraNãoParar #ÉBraide55",
    "hashtags": [
      "ÉTrabalhoSemParar",
      "55PraNãoParar",
      "ÉBraide55"
    ],
    "mentions": [],
    "commentsCount": 188,
    "likesCount": 3231,
    "videoViewCount": 11505,
    "videoPlayCount": 46142,
    "timestamp": "2024-09-15T02:21:33.000Z",
    "ownerFullName": "Eduardo Braide",
    "ownerUsername": "eduardobraide",
    "videoDuration": 150.041
  },
  {
    "type": "Sidecar",
    "caption": "Coração cheio de gratidão pelo carinho que recebemos em mais uma carreata do 5️⃣5️⃣ 💙\n\nObrigada pela recepção, São Raimundo e região! Foi lindo demais estar com vocês! 🫶🏻\n\nPara o trabalho não parar, é @eduardobraide de novo! 💪🏼\n\n#Braide55 #ÉBraideDeNovo #PrefeitoDoPovo #ProTrabalhoContinuar",
    "hashtags": [
      "Braide55",
      "ÉBraideDeNovo",
      "PrefeitoDoPovo",
      "ProTrabalhoContinuar"
    ],
    "mentions": [
      "eduardobraide"
    ],
    "commentsCount": 271,
    "likesCount": 5253,
    "timestamp": "2024-09-15T00:38:35.000Z",
    "ownerFullName": "Dra. Graziela Braide",
    "ownerUsername": "graziela_braide"
  },
  {
    "type": "Video",
    "caption": "✅ Depois da iluminação de LED, centro de saúde e creche de tempo de integral, agora é a vez do asfalto novo aqui no Recanto Verde! \n\n👷🏼E como vocês já sabem, eu sempre fiscalizo tudo para garantir que a obra seja de qualidade.\n\nO meu compromisso com vocês segue é firme! 💪🏽💙\n\n#BraideTrabalha #PrefeitoPresente",
    "hashtags": [
      "BraideTrabalha",
      "PrefeitoPresente"
    ],
    "mentions": [],
    "commentsCount": 326,
    "likesCount": 5015,
    "videoViewCount": 22749,
    "videoPlayCount": 67938,
    "timestamp": "2024-09-16T21:55:23.000Z",
    "ownerFullName": "Eduardo Braide",
    "ownerUsername": "eduardobraide",
    "videoDuration": 25.8
  },
  {
    "type": "Video",
    "caption": "O POVO MOSTRARÁ SUA FORÇA NESSAS ELEIÇÕES!\n\n#ÉTrabalhoSemParar #55PraNãoParar #ÉBraide55",
    "hashtags": [
      "ÉTrabalhoSemParar",
      "55PraNãoParar",
      "ÉBraide55"
    ],
    "mentions": [],
    "commentsCount": 992,
    "likesCount": 8553,
    "videoViewCount": 34622,
    "videoPlayCount": 105543,
    "timestamp": "2024-09-12T18:49:11.000Z",
    "ownerFullName": "Eduardo Braide",
    "ownerUsername": "eduardobraide",
    "videoDuration": 45.125
  },
  {
    "type": "Sidecar",
    "caption": "✅ Participei ontem à noite da Sabatina da @fecomercioma, um importante bate-papo com o setor empresarial sobre o tema “Caminhos para o desenvolvimento”.\n\n📊 Falei sobre como a nossa gestão à frente da Prefeitura vem contribuindo para o desenvolvimento da nossa São Luís e sobre os novos projetos para nossa cidade.\n\nO trabalho por uma São Luís empreendedora, próspera e de oportunidades não para! 💪🏽\n\n#ÉTrabalhoSemParar #55PraNãoParar #ÉBraide55",
    "hashtags": [
      "ÉTrabalhoSemParar",
      "55PraNãoParar",
      "ÉBraide55"
    ],
    "mentions": [
      "fecomercioma,"
    ],
    "commentsCount": 193,
    "likesCount": 4423,
    "timestamp": "2024-09-13T11:10:44.000Z",
    "ownerFullName": "Eduardo Braide",
    "ownerUsername": "eduardobraide"
  },
  {
    "type": "Video",
    "caption": "Só quem vai na carreata do 5️⃣5️⃣ sabe: aqui é diferenciado! 😎\n\nObrigado por todo carinho e apoio, meu São Raimundo e região! Foi lindo demais! 💙\n\n#ÉTrabalhoSemParar #55PraNãoParar #ÉBraide55",
    "hashtags": [
      "ÉTrabalhoSemParar",
      "55PraNãoParar",
      "ÉBraide55"
    ],
    "mentions": [],
    "commentsCount": 633,
    "likesCount": 9897,
    "videoViewCount": 56343,
    "videoPlayCount": 153424,
    "timestamp": "2024-09-15T00:25:47.000Z",
    "ownerFullName": "Eduardo Braide",
    "ownerUsername": "eduardobraide",
    "videoDuration": 75.291
  },
  {
    "type": "Video",
    "caption": "📈 Mais uma pesquisa nacional confirma: é primeiro turno! Obrigado, Deus! Obrigado, minha São Luís! 🙌🏽💙\n\n#ÉTrabalhoSemParar #55PraNãoParar #ÉBraide55",
    "hashtags": [
      "ÉTrabalhoSemParar",
      "55PraNãoParar",
      "ÉBraide55"
    ],
    "mentions": [],
    "commentsCount": 1080,
    "likesCount": 9577,
    "videoViewCount": 44627,
    "videoPlayCount": 179581,
    "timestamp": "2024-09-13T21:46:45.000Z",
    "ownerFullName": "Eduardo Braide",
    "ownerUsername": "eduardobraide",
    "videoDuration": 35.291
  },
  {
    "type": "Video",
    "caption": "📏👷🏼A Santa Efigênia agora tá ficando na régua!\n\n👀 Vim fiscalizar a obra de pavimentação no bairro que tá recebendo 5cm de espessura do #asfaltonovo nas ruas.\n\nA turma do Geniparana não precisa ficar com ciúmes, porque já já a gente chega aí também! 🤣\n\nNosso trabalho por toda São Luís não para! 💙💪🏽\n\n#BraideTrabalha #PrefeitoPresente",
    "hashtags": [
      "asfaltonovo",
      "BraideTrabalha",
      "PrefeitoPresente"
    ],
    "mentions": [],
    "commentsCount": 573,
    "likesCount": 7058,
    "videoViewCount": 29488,
    "videoPlayCount": 90092,
    "timestamp": "2024-09-13T16:52:17.000Z",
    "ownerFullName": "Eduardo Braide",
    "ownerUsername": "eduardobraide",
    "videoDuration": 28.633
  },
  {
    "type": "Video",
    "caption": "💡✨😎 A turma do Residencial Jomar Moraes também já pode separar os óculos escuros!\n\n👀 Fiscalizei agora à noite a instalação da troca da iluminação antiga (luz amarela), pela iluminação de LED que será em todas as ruas do residencial.\n\nAgora diz aí: tá ficando é 🔝, né? 🤩\n\n#BraideTrabalha #PrefeitoPresente",
    "hashtags": [
      "BraideTrabalha",
      "PrefeitoPresente"
    ],
    "mentions": [],
    "commentsCount": 490,
    "likesCount": 7389,
    "videoViewCount": 34043,
    "videoPlayCount": 100449,
    "timestamp": "2024-09-13T02:36:18.000Z",
    "ownerFullName": "Eduardo Braide",
    "ownerUsername": "eduardobraide",
    "videoDuration": 28.083
  },
  {
    "type": "Video",
    "caption": "A Ribeira entrou na 🌊 do 5️⃣5️⃣! \n\n🌟 Estive com @eduardobraide em mais uma carreata linda, recebendo o apoio e carinho do povo que acredita que o trabalho não pode parar! 💪🏽\n\n🗳️ Pro trabalho não parar, é 5️⃣5️⃣ na hora de votar! 💙\n\nVamos em frente e sob as bençãos de Deus e o carinho das pessoas! 🙏🏼\n\n#Braide55 #ProTrabalhoNãoParar #SãoLuísÉ55 #BraideTrabalha",
    "hashtags": [
      "Braide55",
      "ProTrabalhoNãoParar",
      "SãoLuísÉ55",
      "BraideTrabalha"
    ],
    "mentions": [
      "eduardobraide"
    ],
    "commentsCount": 798,
    "likesCount": 11332,
    "videoViewCount": 56703,
    "videoPlayCount": 150718,
    "timestamp": "2024-09-12T02:54:21.000Z",
    "ownerFullName": "Dra. Graziela Braide",
    "ownerUsername": "graziela_braide",
    "videoDuration": 89.2
  },
  {
    "type": "Video",
    "caption": "🤩 O arrastão do 5️⃣5️⃣ chegou com tudo na Liberdade! \n\nA cada sorriso no rosto, a cada abraço apertado, continuamos na certeza de que estamos no caminho certo.\n\nMuito obrigado, minha Liberdade do💙!\n\n#Braide55 #ProTrabalhoNãoParar #SãoLuísÉ55 #BraideTrabalha",
    "hashtags": [
      "Braide55",
      "ProTrabalhoNãoParar",
      "SãoLuísÉ55",
      "BraideTrabalha"
    ],
    "mentions": [],
    "commentsCount": 816,
    "likesCount": 9049,
    "videoViewCount": 44293,
    "videoPlayCount": 128305,
    "timestamp": "2024-09-16T03:29:41.000Z",
    "ownerFullName": "Eduardo Braide",
    "ownerUsername": "eduardobraide",
    "videoDuration": 90.023
  },
  {
    "type": "Video",
    "caption": "👷🏼 O Coroado vai ganhar o 1° Complexo de Educação e Cidadania de São Luís!\n\n✅ Estamos dando vida a esse local abandonado há + de 15 anos com escola, pista de skate, quadra de areia, campo society, quadra coberta, praça de convivência e muito mais!\n\nAté o final do ano, o COMPEC do Coroado será entregue! 💙\n\n#BraideTrabalha #PrefeitoPresente",
    "hashtags": [
      "BraideTrabalha",
      "PrefeitoPresente"
    ],
    "mentions": [],
    "commentsCount": 1087,
    "likesCount": 13143,
    "videoViewCount": 51001,
    "videoPlayCount": 151597,
    "timestamp": "2024-09-12T15:14:35.000Z",
    "ownerFullName": "Eduardo Braide",
    "ownerUsername": "eduardobraide",
    "videoDuration": 43.4
  },
  {
    "type": "Video",
    "caption": "✅ CONCURSOS PÚBLICOS\n\n#TrabalhoSemParar #55PraNãoParar #ÉBraideDeNovo",
    "hashtags": [
      "TrabalhoSemParar",
      "55PraNãoParar",
      "ÉBraideDeNovo"
    ],
    "mentions": [],
    "commentsCount": 1477,
    "likesCount": 12422,
    "videoViewCount": 50884,
    "videoPlayCount": 158228,
    "timestamp": "2024-09-11T14:56:19.000Z",
    "ownerFullName": "Eduardo Braide",
    "ownerUsername": "eduardobraide",
    "videoDuration": 69.433
  },
  {
    "type": "Video",
    "caption": "CIRCO DA CIDADE\n\n#ÉTrabalhoSemParar #55PraNãoParar #ÉBraide55",
    "hashtags": [
      "ÉTrabalhoSemParar",
      "55PraNãoParar",
      "ÉBraide55"
    ],
    "mentions": [],
    "commentsCount": 389,
    "likesCount": 5697,
    "videoViewCount": 25366,
    "videoPlayCount": 87258,
    "timestamp": "2024-09-11T15:52:01.000Z",
    "ownerFullName": "Eduardo Braide",
    "ownerUsername": "eduardobraide",
    "videoDuration": 39.9
  },
  {
    "type": "Video",
    "caption": "Meu Coroadinho segue ficando é no grau! 😎\n\n✅ Vim fiscalizar o resultado do nosso #AsfaltoNovo pra garantir a qualidade:\n\n📍Rua São Sebastião;\n📍Rua da Felicidade;\n📍E a Avenida Amália Saldanha.\n\nNosso trabalho por São Luís não para! 💪🏽\n\n#BraideTrabalha #PrefeitoPresente",
    "hashtags": [
      "AsfaltoNovo",
      "BraideTrabalha",
      "PrefeitoPresente"
    ],
    "mentions": [],
    "commentsCount": 483,
    "likesCount": 7146,
    "videoViewCount": 24871,
    "videoPlayCount": 79222,
    "timestamp": "2024-09-11T14:20:01.000Z",
    "ownerFullName": "Eduardo Braide",
    "ownerUsername": "eduardobraide",
    "videoDuration": 25.733
  },
  {
    "type": "Video",
    "caption": "Carreata na Ribeira! 💙",
    "hashtags": [],
    "mentions": [],
    "commentsCount": 1395,
    "likesCount": 16621,
    "videoViewCount": 46499,
    "videoPlayCount": 143610,
    "timestamp": "2024-09-11T22:13:30.000Z",
    "ownerFullName": "Eduardo Braide",
    "ownerUsername": "eduardobraide",
    "videoDuration": 512.77
  },
  {
    "type": "Video",
    "caption": "😎 A turma do meu João de Deus e do Parque Universitário já podem preparar os óculos escuros pra andar à noite!\n\n✨💡Já terminamos a instalação do LED que chegou em todas as ruas dos bairros.\n\n👀 E eu vou seguir fiscalizando pra tudo ficar de qualidade!\n\n#BraideTrabalha #PrefeitoPresente",
    "hashtags": [
      "BraideTrabalha",
      "PrefeitoPresente"
    ],
    "mentions": [],
    "commentsCount": 1679,
    "likesCount": 19056,
    "videoViewCount": 77579,
    "videoPlayCount": 215387,
    "timestamp": "2024-09-10T01:44:42.000Z",
    "ownerFullName": "Eduardo Braide",
    "ownerUsername": "eduardobraide",
    "videoDuration": 27.166
  },
  {
    "type": "Video",
    "caption": "QUEM NÃO DEVE, NÃO TEME!\n\n#ÉTrabalhoSemParar #55PraNãoParar #ÉBraide55",
    "hashtags": [
      "ÉTrabalhoSemParar",
      "55PraNãoParar",
      "ÉBraide55"
    ],
    "mentions": [],
    "commentsCount": 2046,
    "likesCount": 17769,
    "videoViewCount": 73435,
    "videoPlayCount": 220469,
    "timestamp": "2024-09-11T16:16:10.000Z",
    "ownerFullName": "Eduardo Braide",
    "ownerUsername": "eduardobraide",
    "videoDuration": 64.109
  },
  {
    "type": "Video",
    "caption": "GRANDES EVENTOS\n\n#ÉTrabalhoSemParar #55PraNãoParar #ÉBraide55",
    "hashtags": [
      "ÉTrabalhoSemParar",
      "55PraNãoParar",
      "ÉBraide55"
    ],
    "mentions": [],
    "commentsCount": 688,
    "likesCount": 6666,
    "videoViewCount": 23733,
    "videoPlayCount": 78708,
    "timestamp": "2024-09-11T15:22:37.000Z",
    "ownerFullName": "Eduardo Braide",
    "ownerUsername": "eduardobraide",
    "videoDuration": 69.433
  },
  {
    "type": "Video",
    "caption": "✅ EDUCAÇÃO DE TEMPO INTEGRAL\n\n#ÉTrabalhoSemParar #55PraNãoParar #ÉBraide55",
    "hashtags": [
      "ÉTrabalhoSemParar",
      "55PraNãoParar",
      "ÉBraide55"
    ],
    "mentions": [],
    "commentsCount": 553,
    "likesCount": 4338,
    "videoViewCount": 16428,
    "videoPlayCount": 57690,
    "timestamp": "2024-09-11T16:54:32.000Z",
    "ownerFullName": "Eduardo Braide",
    "ownerUsername": "eduardobraide",
    "videoDuration": 110.291
  },
  {
    "type": "Sidecar",
    "caption": "A gente não para de trabalhar e São Luís não para de avançar, porque o nosso compromisso é com o povo! 💪🏾\n\nÉ 5️⃣5️⃣ na cabeça e no 💙!\n\n#TrabalhoSemParar #55PraNãoParar #ÉBraideDeNovo",
    "hashtags": [
      "TrabalhoSemParar",
      "55PraNãoParar",
      "ÉBraideDeNovo"
    ],
    "mentions": [],
    "commentsCount": 411,
    "likesCount": 5937,
    "timestamp": "2024-09-10T19:58:24.000Z",
    "ownerFullName": "Eduardo Braide",
    "ownerUsername": "eduardobraide"
  },
  {
    "type": "Video",
    "caption": "TRANSPORTE PÚBLICO\n\n#ÉTrabalhoSemParar #55PraNãoParar #ÉBraide55",
    "hashtags": [
      "ÉTrabalhoSemParar",
      "55PraNãoParar",
      "ÉBraide55"
    ],
    "mentions": [],
    "commentsCount": 571,
    "likesCount": 7125,
    "videoViewCount": 28615,
    "videoPlayCount": 96656,
    "timestamp": "2024-09-11T17:53:30.000Z",
    "ownerFullName": "Eduardo Braide",
    "ownerUsername": "eduardobraide",
    "videoDuration": 82.566
  },
  {
    "type": "Image",
    "caption": "💪🏽 O povo de São Luís está mostrando sua força nessa eleição!\n\nA nossa cidade vai continuar melhorando sem parar. Obrigado, Deus. Obrigado, São Luís. Vamos à vitória! 🙏🏽💙👊🏽",
    "hashtags": [],
    "mentions": [],
    "commentsCount": 6033,
    "likesCount": 39640,
    "timestamp": "2024-09-10T00:21:37.000Z",
    "ownerFullName": "Eduardo Braide",
    "ownerUsername": "eduardobraide"
  },
  {
    "type": "Video",
    "caption": "PARCERIA COM O GOVERNO FEDERAL\n\n#ÉTrabalhoSemParar #55PraNãoParar #ÉBraide55",
    "hashtags": [
      "ÉTrabalhoSemParar",
      "55PraNãoParar",
      "ÉBraide55"
    ],
    "mentions": [],
    "commentsCount": 134,
    "likesCount": 3329,
    "videoViewCount": 14756,
    "videoPlayCount": 50827,
    "timestamp": "2024-09-11T17:21:36.000Z",
    "ownerFullName": "Eduardo Braide",
    "ownerUsername": "eduardobraide",
    "videoDuration": 34.533
  },
  {
    "type": "Video",
    "caption": "O sextou é com ponto facultativo, mas o nosso trabalho por São Luís não para, meu povo! 👊🏽\n\n✅ Após anos de espera, a minha Areinha vai ficar é 🔝 com o asfalto novo que chegou com tudo e nos próximos dias, tem iluminação de LED chegando em todas as ruas do bairro.\n\nPor aqui já sabe, né? A fiscalização e o trabalho não param! 💪🏽\n\n#BraideTrabalha #PrefeitoPresente",
    "hashtags": [
      "BraideTrabalha",
      "PrefeitoPresente"
    ],
    "mentions": [],
    "commentsCount": 1179,
    "likesCount": 11798,
    "videoViewCount": 53528,
    "videoPlayCount": 166962,
    "timestamp": "2024-09-06T15:38:58.000Z",
    "ownerFullName": "Eduardo Braide",
    "ownerUsername": "eduardobraide",
    "videoDuration": 33.633
  },
  {
    "type": "Video",
    "caption": "🇧🇷 7 de setembro, Independência do Brasil e, claro, como faço todos os anos vim acompanhar na avenida, o tradicional Desfile da Independência! 👏🏽\n\nÉ sempre muito bonito ver o amor e o significado desta data para nossa história. Viva a nossa pátria amada, viva o Brasil! 💚💛",
    "hashtags": [],
    "mentions": [],
    "commentsCount": 1128,
    "likesCount": 30490,
    "videoViewCount": 123474,
    "videoPlayCount": 337166,
    "timestamp": "2024-09-07T15:07:26.000Z",
    "ownerFullName": "Eduardo Braide",
    "ownerUsername": "eduardobraide",
    "videoDuration": 25.208
  },
  {
    "type": "Video",
    "caption": "✅ Fim dos alagamentos na Vila Conceição e Alto do Calhau! \n\n🚧 Estamos fazendo 1km de drenagem profunda que vai passar pela Av. São Bento e chegar na Rua Colinas.\n\n🛣️ Depois de tudo pronto, tem asfalto novo pra deixar as vias um tapete!\n\nNosso trabalho segue firme! 💪🏽\n\n#BraideTrabalha #PrefeitoPresente",
    "hashtags": [
      "BraideTrabalha",
      "PrefeitoPresente"
    ],
    "mentions": [],
    "commentsCount": 491,
    "likesCount": 7706,
    "videoViewCount": 40823,
    "videoPlayCount": 122447,
    "timestamp": "2024-09-05T17:44:51.000Z",
    "ownerFullName": "Eduardo Braide",
    "ownerUsername": "eduardobraide",
    "videoDuration": 28.133
  },
  {
    "type": "Video",
    "caption": "🌉 Tempo recorde! Em menos de 5 meses do início da obra, o primeiro elevado construído pela Prefeitura de São Luís estará liberado! \n\n✅ Já é neste domingo (8), a partir das 9h, a liberação para o tráfego de veículos em nosso Elevado da Cidade.\n\n🚧 Essa é uma das maiores obras já feitas em nossa cidade que, além de acabar com o engarrafamento da região, será também um novo cartão-postal. \n\nEstamos fazendo o que nunca foi feito por São Luís. ❤️💪🏽\n\n#BraideTrabalha #PrefeitoPresente",
    "hashtags": [
      "BraideTrabalha",
      "PrefeitoPresente"
    ],
    "mentions": [],
    "commentsCount": 5759,
    "likesCount": 45159,
    "videoViewCount": 180122,
    "videoPlayCount": 550533,
    "timestamp": "2024-09-04T15:06:37.000Z",
    "ownerFullName": "Eduardo Braide",
    "ownerUsername": "eduardobraide",
    "videoDuration": 32.1
  },
  {
    "type": "Image",
    "caption": "Noite do Reggae na Jamaica Brasileira! 🇯🇲🤩",
    "hashtags": [],
    "mentions": [],
    "commentsCount": 282,
    "likesCount": 11866,
    "timestamp": "2024-09-04T03:26:44.000Z",
    "ownerFullName": "Eduardo Braide",
    "ownerUsername": "eduardobraide"
  },
  {
    "type": "Sidecar",
    "caption": "🌟 São Luís é feita de histórias e tradições que foram construídas ao longo do tempo por pessoas fortes e acolhedoras e que, hoje, são parte fundamental dessa trajetória. \n\nE celebrar a nossa cidade, é também cuidar, todos os dias, de cada uma das pessoas que nasceram aqui ou escolheram São Luís como lar. 🏠 \n\nParabéns, minha São Luís, pelos seus 412 anos. Que possamos seguir, te celebrando todos os dias e cuidando, ainda mais, da nossa gente! 🫂💙\n\n#SãoLuís412Anos",
    "hashtags": [
      "SãoLuís412Anos"
    ],
    "mentions": [],
    "commentsCount": 364,
    "likesCount": 15029,
    "timestamp": "2024-09-08T12:55:41.000Z",
    "ownerFullName": "Dra. Graziela Braide",
    "ownerUsername": "graziela_braide"
  },
  {
    "type": "Video",
    "caption": "Parabéns, minha São Luís! 🎂👏🏽❤️",
    "hashtags": [],
    "mentions": [],
    "commentsCount": 633,
    "likesCount": 7376,
    "videoViewCount": 26334,
    "videoPlayCount": 101914,
    "timestamp": "2024-09-07T23:55:22.000Z",
    "ownerFullName": "Eduardo Braide",
    "ownerUsername": "eduardobraide",
    "videoDuration": 150.041
  },
  {
    "type": "Video",
    "caption": "🚍 🛣️😎 Podem pegar o Guanabara e vir tranquilo, porque depois de 20 anos de espera, o asfalto novo tá ficando é na régua aqui no Parque Guanabara!\n\n✨💡Fiscalizei hoje a pavimentação que vai chegar em todas as ruas do bairro e depois tem iluminação de LED! \n\nSeguimos trabalhando firme e fazendo o que nunca foi feito por São Luís! ❤️\n\n#BraideTrabalha #PrefeitoPresente",
    "hashtags": [
      "BraideTrabalha",
      "PrefeitoPresente"
    ],
    "mentions": [],
    "commentsCount": 1285,
    "likesCount": 13930,
    "videoViewCount": 64293,
    "videoPlayCount": 188886,
    "timestamp": "2024-09-05T14:50:42.000Z",
    "ownerFullName": "Eduardo Braide",
    "ownerUsername": "eduardobraide",
    "videoDuration": 29.566
  },
  {
    "type": "Image",
    "caption": "",
    "hashtags": [],
    "mentions": [],
    "commentsCount": 1220,
    "likesCount": 17903,
    "timestamp": "2024-09-05T16:29:07.000Z",
    "ownerFullName": "Eduardo Braide",
    "ownerUsername": "eduardobraide"
  },
  {
    "type": "Sidecar",
    "caption": "⛪️ Como todos os anos, iniciei o dia do aniversário da nossa São Luís agradecendo a Deus pelos seus 4️⃣1️⃣2️⃣ anos!\n\nEm celebração presidida por @dompastana, agradeci por todas as bençãos alcançadas em nossa cidade e pedi também que os dias sejam de luz e prosperidade para os ludovicenses.\n\nQue Deus abençoe a nossa cidade! 🙏🏽❤️",
    "hashtags": [],
    "mentions": [
      "dompastana,"
    ],
    "commentsCount": 492,
    "likesCount": 18229,
    "timestamp": "2024-09-08T19:38:29.000Z",
    "ownerFullName": "Eduardo Braide",
    "ownerUsername": "eduardobraide"
  },
  {
    "type": "Image",
    "caption": "#BraideTrabalha #PrefeitoPresente",
    "hashtags": [
      "BraideTrabalha",
      "PrefeitoPresente"
    ],
    "mentions": [],
    "commentsCount": 202,
    "likesCount": 4796,
    "timestamp": "2024-09-09T13:31:45.000Z",
    "ownerFullName": "Eduardo Braide",
    "ownerUsername": "eduardobraide"
  },
  {
    "type": "Sidecar",
    "caption": "💙 Gratidão, minha Área Itaqui-Bacanga!\n\nFoi bom demais receber todo esse carinho de vocês durante a nossa carreata do 5️⃣5️⃣. Essa é a confirmação que estamos no caminho certo.🤩\n\nSeguimos firmes na nossa missão de cuidar da nossa cidade e das pessoas! 💪🏽\n\n#ÉTrabalhoSemParar #55PraContinuar #ÉBraideDeNovo",
    "hashtags": [
      "ÉTrabalhoSemParar",
      "55PraContinuar",
      "ÉBraideDeNovo"
    ],
    "mentions": [],
    "commentsCount": 494,
    "likesCount": 12903,
    "timestamp": "2024-09-01T20:11:58.000Z",
    "ownerFullName": "Eduardo Braide",
    "ownerUsername": "eduardobraide"
  },
  {
    "type": "Video",
    "caption": "✅ Tudo no ponto pra amanhã, meu povo! \n\nNeste domingo (8 de setembro), a partir das 9h da manhã, nosso Elevado da Cidade estará liberado e anotem aí: o trânsito vai ficar é livre em toda região! 🤩\n\n#BraideTrabalha #PrefeitoPresente",
    "hashtags": [
      "BraideTrabalha",
      "PrefeitoPresente"
    ],
    "mentions": [],
    "commentsCount": 3280,
    "likesCount": 31104,
    "videoViewCount": 144558,
    "videoPlayCount": 447139,
    "timestamp": "2024-09-07T17:14:00.000Z",
    "ownerFullName": "Eduardo Braide",
    "ownerUsername": "eduardobraide",
    "videoDuration": 54.266
  },
  {
    "type": "Video",
    "caption": "☀️ Começando a semana especial de aniversário da nossa São Luís com muito trabalho, alegria e novidades!\n\n✅ Agora pela manhã participo das sabatinas na Universidade FM às 9h e TV UFMA às 12h30, falando de tudo o que já fizemos e de muito mais que tá vindo aí;\n\n🎂 Ao longo da semana teremos as comemorações na Praia Grande;\n\n🎁 E nos próximos dias ainda tem um presentão pra nossa cidade. Fiquem ligados!\n\nQue Deus nos abençoe e um abração pra vocês! 💙\n\n#BraideTrabalha #PrefeitoPresente",
    "hashtags": [
      "BraideTrabalha",
      "PrefeitoPresente"
    ],
    "mentions": [],
    "commentsCount": 984,
    "likesCount": 14984,
    "videoViewCount": 65649,
    "videoPlayCount": 198247,
    "timestamp": "2024-09-02T12:08:31.000Z",
    "ownerFullName": "Eduardo Braide",
    "ownerUsername": "eduardobraide",
    "videoDuration": 52.5
  },
  {
    "type": "Video",
    "caption": "Já fizemos muito e vamos fazer muito mais! \n\n✅ Novo Hospital da Criança; \n\n✅+ de 6⃣0⃣0⃣ km de Asfalto Novo;\n\n✅ Iluminação de LED;\n\n✅ 06 Creches de Tempo Integral.\n\nPro trabalho não parar, é 5⃣5⃣ na hora de votar! 💙💪🏽\n\n#TrabalhoSemParar #55PraNãoParar #ÉBraideDeNovo",
    "hashtags": [
      "TrabalhoSemParar",
      "55PraNãoParar",
      "ÉBraideDeNovo"
    ],
    "mentions": [],
    "commentsCount": 452,
    "likesCount": 5901,
    "videoViewCount": 20364,
    "videoPlayCount": 94517,
    "timestamp": "2024-09-03T11:13:23.000Z",
    "ownerFullName": "Eduardo Braide",
    "ownerUsername": "eduardobraide",
    "videoDuration": 153.041
  },
  {
    "type": "Image",
    "caption": "Noite linda dos povos de axé com a nossa vice-prefeita, @esmenia.miranda. Axé, São Luís! 📿✊🏿",
    "hashtags": [],
    "mentions": [
      "esmenia.miranda."
    ],
    "commentsCount": 173,
    "likesCount": 7614,
    "timestamp": "2024-09-03T01:50:07.000Z",
    "ownerFullName": "Eduardo Braide",
    "ownerUsername": "eduardobraide"
  },
  {
    "type": "Video",
    "caption": "✨Quando menos vocês esperarem, o LED vai chegar na rua de vocês!\n\n🛣️💡Depois do asfalto novo nas ruas do residenciais Ecopark e Eco Space, chegou a vez da nossa iluminação de LED! \n\nA turma já pode separar o óculos escuro, porque a noite já tá é parecendo dia!☀️😎\n\n#BraideTrabalha #PrefeitoPresente",
    "hashtags": [
      "BraideTrabalha",
      "PrefeitoPresente"
    ],
    "mentions": [],
    "commentsCount": 1602,
    "likesCount": 22716,
    "videoViewCount": 123540,
    "videoPlayCount": 330474,
    "timestamp": "2024-08-31T02:30:15.000Z",
    "ownerFullName": "Eduardo Braide",
    "ownerUsername": "eduardobraide",
    "videoDuration": 24.466
  },
  {
    "type": "Video",
    "caption": "Já fizemos muito, mas podem ter certeza: ainda faremos muito mais, São Luís! 💙\n\nPro trabalho não parar, é 5⃣5⃣ na hora de votar! 💪🏽\n\n#TrabalhoSemParar #55PraNãoParar #ÉBraideDeNovo",
    "hashtags": [
      "TrabalhoSemParar",
      "55PraNãoParar",
      "ÉBraideDeNovo"
    ],
    "mentions": [],
    "commentsCount": 439,
    "likesCount": 5244,
    "videoViewCount": 20156,
    "videoPlayCount": 111511,
    "timestamp": "2024-08-31T23:45:53.000Z",
    "ownerFullName": "Eduardo Braide",
    "ownerUsername": "eduardobraide",
    "videoDuration": 150.125
  },
  {
    "type": "Video",
    "caption": "👩🏻‍🏫👨🏽‍🏫 Vem aí +1 concurso da Prefeitura: 6️⃣0️⃣0️⃣ vagas para professor + cadastro de reserva! \n\nVão se preparando, porque logo logo o edital será publicado. Bons estudos! 📚😉\n\nNosso trabalho por uma educação de qualidade e oportunidades segue firme! 💪🏽\n\n#BraideTrabalha #PrefeitoPresente",
    "hashtags": [
      "BraideTrabalha",
      "PrefeitoPresente"
    ],
    "mentions": [],
    "commentsCount": 1820,
    "likesCount": 24543,
    "videoViewCount": 102829,
    "videoPlayCount": 308165,
    "timestamp": "2024-08-29T18:39:18.000Z",
    "ownerFullName": "Eduardo Braide",
    "ownerUsername": "eduardobraide",
    "videoDuration": 35.633
  },
  {
    "type": "Video",
    "caption": "Meu país Cohatrac é diferenciado! 😎\n\nA nossa 🌊 do 5️⃣5️⃣ tomou conta e encheu as ruas do bairro com muito amor, alegria, gratidão e um único sentimento: o trabalho por São Luís não pode parar! \n\nPro trabalho não parar, é 5️⃣5️⃣ na hora de votar! 💪🏽\n\n#TrabalhoSemParar #55PraContinuar #ÉBraideDeNovo",
    "hashtags": [
      "TrabalhoSemParar",
      "55PraContinuar",
      "ÉBraideDeNovo"
    ],
    "mentions": [],
    "commentsCount": 1167,
    "likesCount": 17573,
    "videoViewCount": 70903,
    "videoPlayCount": 233618,
    "timestamp": "2024-08-31T19:40:53.000Z",
    "ownerFullName": "Eduardo Braide",
    "ownerUsername": "eduardobraide",
    "videoDuration": 57.333
  },
  {
    "type": "Video",
    "caption": "👷‍♂️🔍 Se o trabalho não para, a fiscalização também não! \n\n🛣️ Após anos de espera, o Gapara tá ganhando 58 ruas com asfalto novo e de qualidade. \n\nEstamos fazendo o que nunca foi feito em São Luís. Me ajudem a fiscalizar as obras também! 💪🏽\n\n#BraideTrabalha\n#PrefeitoPresente",
    "hashtags": [
      "BraideTrabalha",
      "PrefeitoPresente"
    ],
    "mentions": [],
    "commentsCount": 805,
    "likesCount": 10890,
    "videoViewCount": 45836,
    "videoPlayCount": 152911,
    "timestamp": "2024-08-30T15:54:21.000Z",
    "ownerFullName": "Eduardo Braide",
    "ownerUsername": "eduardobraide",
    "videoDuration": 30.488
  },
  {
    "type": "Video",
    "caption": "👮🏻👮🏽‍♂️ Dia Nacional do Guarda Municipal! \n\n👏🏽 Meus parabéns a todos os nossos guardas municipais pelo grande trabalho realizado todos os dias em São Luís.\n\n✅ E tem reforço chegando: autorizamos a chamada de + 1️⃣0️⃣0️⃣ novos guardas aprovados no nosso último concurso. \n\nSeguiremos trabalhando firme pela segurança em nossa cidade! 💪🏾 \n\n#BraideTrabalha #PrefeitoPresente",
    "hashtags": [
      "BraideTrabalha",
      "PrefeitoPresente"
    ],
    "mentions": [],
    "commentsCount": 666,
    "likesCount": 11869,
    "videoViewCount": 52148,
    "videoPlayCount": 158549,
    "timestamp": "2024-09-03T13:39:08.000Z",
    "ownerFullName": "Eduardo Braide",
    "ownerUsername": "eduardobraide",
    "videoDuration": 33.708
  },
  {
    "type": "Video",
    "caption": "📺🤩 Assista nosso primeiro programa na TV!\n\n#TrabalhoSemParar #55PraNãoParar #ÉBraideDeNovo",
    "hashtags": [
      "TrabalhoSemParar",
      "55PraNãoParar",
      "ÉBraideDeNovo"
    ],
    "mentions": [],
    "commentsCount": 892,
    "likesCount": 7578,
    "videoViewCount": 43912,
    "videoPlayCount": 399287,
    "timestamp": "2024-08-30T19:56:45.000Z",
    "ownerFullName": "Eduardo Braide",
    "ownerUsername": "eduardobraide",
    "videoDuration": 150.375
  },
  {
    "type": "Video",
    "caption": "✅️👊🏽 Vai ter Aniversário da Cidade Sim!\n\n#SãoLuís412Anos",
    "hashtags": [
      "SãoLuís412Anos"
    ],
    "mentions": [],
    "commentsCount": 5041,
    "likesCount": 47597,
    "videoViewCount": 173645,
    "videoPlayCount": 523568,
    "timestamp": "2024-08-29T15:28:03.000Z",
    "ownerFullName": "Eduardo Braide",
    "ownerUsername": "eduardobraide",
    "videoDuration": 40.356
  },
  {
    "type": "Video",
    "caption": "São Luís é 5️⃣5️⃣, porque a transformação da nossa cidade não pode parar! 🤩\n\n✅ Nossa 1ª grande caminhada na Rua Grande foi linda e o meu coração é só gratidão. \n\nVamos juntos mostrar a força do povo! ❤️\n\n#TrabalhoSemParar\n#55PraContinuar #ÉBraideDeNovo",
    "hashtags": [
      "TrabalhoSemParar",
      "55PraContinuar",
      "ÉBraideDeNovo"
    ],
    "mentions": [],
    "commentsCount": 2864,
    "likesCount": 26024,
    "videoViewCount": 82060,
    "videoPlayCount": 259368,
    "timestamp": "2024-08-23T23:21:47.000Z",
    "ownerFullName": "Eduardo Braide",
    "ownerUsername": "eduardobraide",
    "videoDuration": 60.533
  },
  {
    "type": "Video",
    "caption": "🤩 Adivinhem aí o dia que Elevado da Cidade já vai estar liberado pra vocês passarem por cima…\n\n✅🏗️ Já estamos na fase final dessa grande obra que além de acabar com o engarrafamento da região, será o novo cartão-postal.\n\nEstamos trabalhando muito e fazendo o que nunca foi feito antes pela nossa São Luís.❤️💪🏽\n\n#BraideTrabalha #PrefeitoPresente",
    "hashtags": [
      "BraideTrabalha",
      "PrefeitoPresente"
    ],
    "mentions": [],
    "commentsCount": 2614,
    "likesCount": 25796,
    "videoViewCount": 105661,
    "videoPlayCount": 329629,
    "timestamp": "2024-08-27T15:50:49.000Z",
    "ownerFullName": "Eduardo Braide",
    "ownerUsername": "eduardobraide",
    "videoDuration": 30.633
  },
  {
    "type": "Video",
    "caption": "😋🥟 Prefeito de vocês já lanchou e hoje foi aqui na @princesadossalgados1, no meu país Cidade Operarária! Quem aí já meteu um lanchão 🔝 aqui?",
    "hashtags": [],
    "mentions": [
      "princesadossalgados1,"
    ],
    "commentsCount": 1231,
    "likesCount": 25444,
    "videoViewCount": 120185,
    "videoPlayCount": 337036,
    "timestamp": "2024-08-27T20:51:38.000Z",
    "ownerFullName": "Eduardo Braide",
    "ownerUsername": "eduardobraide",
    "videoDuration": 22.8
  },
  {
    "type": "Video",
    "caption": "Se não dá tempo de jantar, a gente desenrola logo é um lanche no carro🤣! Vai um nikito com coca gelada?",
    "hashtags": [],
    "mentions": [],
    "commentsCount": 2551,
    "likesCount": 25120,
    "videoViewCount": 96848,
    "videoPlayCount": 315359,
    "timestamp": "2024-08-24T22:26:56.000Z",
    "ownerFullName": "Eduardo Braide",
    "ownerUsername": "eduardobraide",
    "videoDuration": 26.285
  },
  {
    "type": "Video",
    "caption": "✨💡Pareceu mágica, né? Mas é trabalho: minha Vila Palmeira vai ficar toda no LED! \n\n✅ Fechando a sexta com essa notícia boa para os moradores, porque vamos chegar em todas as ruas do bairro. \n\nO trabalho não para! ❤️💪🏽\n\n#BraideTrabalha #PrefeitoPresente",
    "hashtags": [
      "BraideTrabalha",
      "PrefeitoPresente"
    ],
    "mentions": [],
    "commentsCount": 1100,
    "likesCount": 11416,
    "videoViewCount": 48502,
    "videoPlayCount": 168319,
    "timestamp": "2024-08-24T02:01:33.000Z",
    "ownerFullName": "Eduardo Braide",
    "ownerUsername": "eduardobraide",
    "videoDuration": 33.7
  },
  {
    "type": "Video",
    "caption": "😎O Anilzão botou foi pra estralar na nossa caminhada do 5️⃣5️⃣!!! \n\nMeu coração é só gratidão por receber o carinho de vocês nas ruas e a confirmação que o nosso trabalho não pode parar. \n\nO povo é quem manda! Pra cima, São Luís! ❤️💪🏽\n\n#TrabalhoSemParar #55PraNãoParar #ÉBraideDeNovo",
    "hashtags": [
      "TrabalhoSemParar",
      "55PraNãoParar",
      "ÉBraideDeNovo"
    ],
    "mentions": [],
    "commentsCount": 891,
    "likesCount": 11816,
    "videoViewCount": 50267,
    "videoPlayCount": 166658,
    "timestamp": "2024-08-25T19:11:01.000Z",
    "ownerFullName": "Eduardo Braide",
    "ownerUsername": "eduardobraide",
    "videoDuration": 56.5
  },
  {
    "type": "Video",
    "caption": "😎 Alô, minha Cohab! Coloca os óculos escuros porque a noite vai virar dia! \n\n☀️ A Cohab e os conjuntos Cohab Anil I, II, III e IV vão ficar todos no LED.\n\n👀 E eu vou seguir fiscalizando pra tudo ficar de qualidade!\n \n#BraideTrabalha #PrefeitoPresente",
    "hashtags": [
      "BraideTrabalha",
      "PrefeitoPresente"
    ],
    "mentions": [],
    "commentsCount": 2663,
    "likesCount": 24845,
    "videoViewCount": 103636,
    "videoPlayCount": 298553,
    "timestamp": "2024-08-29T01:16:58.000Z",
    "ownerFullName": "Eduardo Braide",
    "ownerUsername": "eduardobraide",
    "videoDuration": 31.253
  },
  {
    "type": "Video",
    "caption": "🛣️ Depois de + de 25 anos de espera, olha o asfalto novo chegando em todas as ruas do Solar dos Lusitanos! \n\n✅ Aqui é trabalho de qualidade e com 5cm de asfalto britado feito para durar. Então, não deixem mais ninguém quebrar a rua. 🤭\n\nA iluminação de LED também tá vindo e assim seguimos fazendo pela nossa São Luís o que nunca tinha sido feito! ❤️💪🏽\n\n#BraideTrabalha #PrefeitoPresente",
    "hashtags": [
      "BraideTrabalha",
      "PrefeitoPresente"
    ],
    "mentions": [],
    "commentsCount": 1500,
    "likesCount": 14611,
    "videoViewCount": 70591,
    "videoPlayCount": 205898,
    "timestamp": "2024-08-28T16:05:24.000Z",
    "ownerFullName": "Eduardo Braide",
    "ownerUsername": "eduardobraide",
    "videoDuration": 44.9
  },
  {
    "type": "Video",
    "caption": "👷🏼‍♂️Compromisso é compromisso: nosso trabalho não para por conta de campanha! \n\n🤩 Meu São Bernardo tá se transformando com a iluminação de LED e com o asfalto novo, como o que tá chegando aqui na Rua 48! \n\nSigo fiscalizando pessoalmente as obras!❤️💪🏽\n\n#BraideTrabalha #PrefeitoPresente",
    "hashtags": [
      "BraideTrabalha",
      "PrefeitoPresente"
    ],
    "mentions": [],
    "commentsCount": 900,
    "likesCount": 10211,
    "videoViewCount": 40723,
    "videoPlayCount": 128213,
    "timestamp": "2024-08-24T15:28:32.000Z",
    "ownerFullName": "Eduardo Braide",
    "ownerUsername": "eduardobraide",
    "videoDuration": 38.433
  },
  {
    "type": "Video",
    "caption": "📣 Tamo chegando, Rua Grande!!!\n\nA nossa 1ª grande caminhada do 5️⃣5️⃣ é hoje, a partir das 16h e a concentração é no Largo do Carmo!\n\nVai ser lindo e eu espero vocês lá! ❤️🤩\n\n#TrabalhoSemParar #55PraContinuar #ÉBraideDeNovo",
    "hashtags": [
      "TrabalhoSemParar",
      "55PraContinuar",
      "ÉBraideDeNovo"
    ],
    "mentions": [],
    "commentsCount": 1428,
    "likesCount": 20451,
    "videoViewCount": 88668,
    "videoPlayCount": 269244,
    "timestamp": "2024-08-23T15:02:25.000Z",
    "ownerFullName": "Eduardo Braide",
    "ownerUsername": "eduardobraide",
    "videoDuration": 29.791
  },
  {
    "type": "Video",
    "caption": "Equipe montada, projetos prontos e recursos assegurados: São Luís vai viver seus melhores anos nos próximos quatro anos! ❤️💪🏽✅",
    "hashtags": [],
    "mentions": [],
    "commentsCount": 1739,
    "likesCount": 12870,
    "videoViewCount": 47541,
    "videoPlayCount": 161905,
    "timestamp": "2024-08-28T17:07:24.000Z",
    "ownerFullName": "Eduardo Braide",
    "ownerUsername": "eduardobraide",
    "videoDuration": 57.733
  },
  {
    "type": "Video",
    "caption": "💡🤩 Fechando o sabadão na Alemanha, acompanhando de perto o resultado da nova iluminação de LED! \n\nTá lindo demais e agora, a noite parece dia. É mais qualidade de vida e segurança pra população! ✨\n\n#BraideTrabalha #PrefeitoPresente",
    "hashtags": [
      "BraideTrabalha",
      "PrefeitoPresente"
    ],
    "mentions": [],
    "commentsCount": 674,
    "likesCount": 9231,
    "videoViewCount": 38391,
    "videoPlayCount": 124735,
    "timestamp": "2024-08-25T01:39:07.000Z",
    "ownerFullName": "Eduardo Braide",
    "ownerUsername": "eduardobraide",
    "videoDuration": 24.266
  },
  {
    "type": "Video",
    "caption": "🌙💡✨O boa noite iluminado de hoje é diretamente daqui da minha Vila Brasil e São Bernardo, que agora vão ficar com todas as ruas no LED.\n\nJá dá pra notar a diferença da luz antiga (amarela) para a luz de LED. Agora diz aí: nossa cidade tá cada dia mais linda, né? 🤩❤️\n\n#BraideTrabalha #PrefeitoPresente",
    "hashtags": [
      "BraideTrabalha",
      "PrefeitoPresente"
    ],
    "mentions": [],
    "commentsCount": 1422,
    "likesCount": 13891,
    "videoViewCount": 58819,
    "videoPlayCount": 176486,
    "timestamp": "2024-08-22T02:03:35.000Z",
    "ownerFullName": "Eduardo Braide",
    "ownerUsername": "eduardobraide",
    "videoDuration": 38.133
  },
  {
    "type": "Video",
    "caption": "👷🏼‍♂️Os alagamentos históricos da Av. Joaquim Mochel vão acabar!\n\n✅ Além do asfalto novo que tá chegando em toda a avenida, estamos fazendo a tão esperada obra de drenagem profunda no trecho que sempre causou transtornos com alagamentos. \n\nSeguimos fazendo o que nunca foi feito por São Luís! ❤️💪🏽\n\n#BraideTrabalha #PrefeitoPresente",
    "hashtags": [
      "BraideTrabalha",
      "PrefeitoPresente"
    ],
    "mentions": [],
    "commentsCount": 783,
    "likesCount": 9641,
    "videoViewCount": 52384,
    "videoPlayCount": 150829,
    "timestamp": "2024-08-22T14:21:04.000Z",
    "ownerFullName": "Eduardo Braide",
    "ownerUsername": "eduardobraide",
    "videoDuration": 34.6
  },
  {
    "type": "Video",
    "caption": "📣 Quem tá com a gente faz o 5️⃣5️⃣ e manda um 🫶🏽 aí!!\n\n#TrabalhoSemParar #55PraContinuar #ÉBraideDeNovo",
    "hashtags": [
      "TrabalhoSemParar",
      "55PraContinuar",
      "ÉBraideDeNovo"
    ],
    "mentions": [],
    "commentsCount": 1868,
    "likesCount": 16519,
    "videoViewCount": 59004,
    "videoPlayCount": 203036,
    "timestamp": "2024-08-19T16:51:10.000Z",
    "ownerFullName": "Eduardo Braide",
    "ownerUsername": "eduardobraide",
    "videoDuration": 21.633
  },
  {
    "type": "Video",
    "caption": "🏗️👷🏼‍♂️ Avisa aí que o nosso Elevado da Cidade já vai tá liberado no mês que vem!\n\n✅ Vamos acabar de uma vez por todas com o engarrafamento nessa região. Seguirei acompanhando toda obra, porque aqui não será só um elevado, será o novo cartão postal da cidade!❤️\n\n#TrabalhoSemParar #55PraContinuar #ÉBraideDeNovo",
    "hashtags": [
      "TrabalhoSemParar",
      "55PraContinuar",
      "ÉBraideDeNovo"
    ],
    "mentions": [],
    "commentsCount": 2922,
    "likesCount": 27693,
    "videoViewCount": 112940,
    "videoPlayCount": 348050,
    "timestamp": "2024-08-20T14:54:31.000Z",
    "ownerFullName": "Eduardo Braide",
    "ownerUsername": "eduardobraide",
    "videoDuration": 22.933
  },
  {
    "type": "Image",
    "caption": "",
    "hashtags": [],
    "mentions": [],
    "commentsCount": 462,
    "likesCount": 7666,
    "timestamp": "2024-08-23T11:15:33.000Z",
    "ownerFullName": "Eduardo Braide",
    "ownerUsername": "eduardobraide"
  },
  {
    "type": "Video",
    "caption": "Temos a gestão mais eficiente do Brasil! 🤩\n\n📊 O @poder360 divulgou a análise feita entre as capitais sobre o superávit financeiro, ou seja, o resultado de tudo foi arrecadado X tudo que foi gasto pelos municípios.\n\n✅ São Luís teve o melhor desempenho, aumentando a capacidade de investimentos e sem aumentar impostos! Isso é boa gestão e responsabilidade com os recursos públicos. Por isso, temos tantas obras sendo feitas na cidade só com recursos da Prefeitura! \n\nAinda vamos fazer muito mais! Na hora de votar, é 5⃣5⃣ para o trabalho não parar! 💪🏽❤️\n\n#TrabalhoSemParar #GestãoEficiente",
    "hashtags": [
      "TrabalhoSemParar",
      "GestãoEficiente"
    ],
    "mentions": [
      "poder360"
    ],
    "commentsCount": 663,
    "likesCount": 7818,
    "videoViewCount": 73126,
    "videoPlayCount": 239176,
    "timestamp": "2024-08-18T20:14:52.000Z",
    "ownerFullName": "Eduardo Braide",
    "ownerUsername": "eduardobraide",
    "videoDuration": 28.025
  },
  {
    "type": "Video",
    "caption": "🤠👢🐎 Expoema 2024: mais um ano de parceria firmada!\n\n🤝🏽A Prefeitura é parceira da 64ª edição da @expoemaoficial. Os detalhes foram firmados durante reunião hoje com a diretoria da @ascem.ma. \n\n🗓 A Expoema será de 1º a 8 de setembro, no Parque Independência. Então, preparem a bota e o chapéu para curtir esse evento que faz parte da história da nossa cidade! \n\n#BraideTrabalha #PrefeitoPresente",
    "hashtags": [
      "BraideTrabalha",
      "PrefeitoPresente"
    ],
    "mentions": [
      "expoemaoficial.",
      "ascem.ma."
    ],
    "commentsCount": 330,
    "likesCount": 10967,
    "videoViewCount": 68918,
    "videoPlayCount": 184223,
    "timestamp": "2024-08-19T14:23:50.000Z",
    "ownerFullName": "Eduardo Braide",
    "ownerUsername": "eduardobraide",
    "videoDuration": 27.305
  },
  {
    "type": "Video",
    "caption": "Absurdo! Querem cancelar o aniversário de São Luís.",
    "hashtags": [],
    "mentions": [],
    "commentsCount": 7987,
    "likesCount": 51842,
    "videoViewCount": 213249,
    "videoPlayCount": 665431,
    "timestamp": "2024-08-22T22:04:26.000Z",
    "ownerFullName": "Eduardo Braide",
    "ownerUsername": "eduardobraide",
    "videoDuration": 83.615
  },
  {
    "type": "Video",
    "caption": "✅ Seja com asfalto novo ou concreto, o serviço tem que ser de qualidade! \n\n🚧 Aqui na Rua da Subestação (São Bernardo), na Forquilha, nossa equipe de engenharia avaliou todos os serviços necessários e o tipo de pavimentação. Estamos fazendo uma laje de concreto com 20cm pra acabar com os buracos e transtornos históricos. \n\nSeguimos fazendo o que nunca foi feito por São Luís! ❤️\n\n#BraideTrabalha\n#PrefeitoPresente",
    "hashtags": [
      "BraideTrabalha",
      "PrefeitoPresente"
    ],
    "mentions": [],
    "commentsCount": 1855,
    "likesCount": 18129,
    "videoViewCount": 84162,
    "videoPlayCount": 248057,
    "timestamp": "2024-08-21T13:57:49.000Z",
    "ownerFullName": "Eduardo Braide",
    "ownerUsername": "eduardobraide",
    "videoDuration": 47.266
  },
  {
    "type": "Video",
    "caption": "Acalmem o coração de vocês que já já, as caminhadas e carreatas vão começar, meu povo!🤩🤣\n\nÉ que é muito trabalho pra acompamhar e hoje foi a vez de fiscalizar a chegada do #AsfaltoNovo no Planalto Anil III. Agora, os buracos e a poeira vão ficar no passado! E depois chega o LED em todo bairro! 😉💪🏽\n\n#TrabalhoSemParar #PrefeitoPresente",
    "hashtags": [
      "AsfaltoNovo",
      "TrabalhoSemParar",
      "PrefeitoPresente"
    ],
    "mentions": [],
    "commentsCount": 756,
    "likesCount": 10516,
    "videoViewCount": 46177,
    "videoPlayCount": 142880,
    "timestamp": "2024-08-17T16:02:00.000Z",
    "ownerFullName": "Eduardo Braide",
    "ownerUsername": "eduardobraide",
    "videoDuration": 35.633
  },
  {
    "type": "Sidecar",
    "caption": "Segue a ação ajuizada às 13h09 de ontem (21/08/2024) pela Coligação Juntos Por São Luís (Duarte Jr), que pede à justiça o cancelamento do aniversário de São Luís (Edital de Chamento Público n° 03/2024).",
    "hashtags": [],
    "mentions": [],
    "commentsCount": 2230,
    "likesCount": 17012,
    "timestamp": "2024-08-23T00:22:48.000Z",
    "ownerFullName": "Eduardo Braide",
    "ownerUsername": "eduardobraide"
  },
  {
    "type": "Sidecar",
    "caption": "🙌🏽 Finalizei ontem o sábado participando da 29º Cruzada Evangelística Jesus Cristo, o Senhor da Vida, na Vila Brasil!\n\n🙏🏽 Grande momento de fé e louvor que já faz parte do calendário ludovicense. Agradeço o convite do @prluisrios e o parabenizo por mais esta realização.\n\nA toda @advilabrasil, muito obrigado pelo carinho e que Deus nos abençoando sempre! ❤️\n\n#AFéNosMove",
    "hashtags": [
      "AFéNosMove"
    ],
    "mentions": [
      "prluisrios",
      "advilabrasil,"
    ],
    "commentsCount": 176,
    "likesCount": 5841,
    "timestamp": "2024-08-18T12:06:51.000Z",
    "ownerFullName": "Eduardo Braide",
    "ownerUsername": "eduardobraide"
  },
  {
    "type": "Video",
    "caption": "✅ O trabalho que tá transformando São Luis não pode parar! Na hora de votar, é 5️⃣5️⃣ pra continuar!\n\n#TrabalhoSemParar #ÉBraideDeNovo",
    "hashtags": [
      "TrabalhoSemParar",
      "ÉBraideDeNovo"
    ],
    "mentions": [],
    "commentsCount": 1987,
    "likesCount": 16211,
    "videoViewCount": 59587,
    "videoPlayCount": 211926,
    "timestamp": "2024-08-16T04:23:00.000Z",
    "ownerFullName": "Eduardo Braide",
    "ownerUsername": "eduardobraide",
    "videoDuration": 94.388
  },
  {
    "type": "Video",
    "caption": "Tenho um pedido pra vocês. Assistam o vídeo até o final e me respondam. 🤩\n\nE aí, posso contar com vocês? ✋🏽🤚🏽\n\n#TrabalhoSemParar",
    "hashtags": [
      "TrabalhoSemParar"
    ],
    "mentions": [],
    "commentsCount": 3734,
    "likesCount": 27663,
    "videoViewCount": 96054,
    "videoPlayCount": 295921,
    "timestamp": "2024-08-17T02:02:00.000Z",
    "ownerFullName": "Eduardo Braide",
    "ownerUsername": "eduardobraide",
    "videoDuration": 51.833
  },
  {
    "type": "Image",
    "caption": "Hoje o Brasil se despede do grande Silvio Santos, um dos pioneiros da comunicação brasileira! \n\nSilvio era inovador e tinha um jeito único de se comunicar. Fez parte do dia a dia de milhões de telespectadores, trazendo entretenimento e a notícia por meio da sua alegria. \n\nMe solidarizo com o Grupo SBT, familiares, fãs e admiradores do seu trabalho. Você será eterno nos corações dos brasileiros. Descanse em paz, Silvio!",
    "hashtags": [],
    "mentions": [],
    "commentsCount": 326,
    "likesCount": 14968,
    "timestamp": "2024-08-17T14:13:24.000Z",
    "ownerFullName": "Eduardo Braide",
    "ownerUsername": "eduardobraide"
  },
  {
    "type": "Image",
    "caption": "✅ O trabalho que tá transformando São Luis não pode parar! Na hora de votar, é 5️⃣5️⃣ pra continuar!\n\n#TrabalhoSemParar #ÉBraideDeNovo",
    "hashtags": [
      "TrabalhoSemParar",
      "ÉBraideDeNovo"
    ],
    "mentions": [],
    "commentsCount": 1281,
    "likesCount": 14832,
    "timestamp": "2024-08-16T13:04:10.000Z",
    "ownerFullName": "Eduardo Braide",
    "ownerUsername": "eduardobraide"
  }
]